{
  "名前": "マリアの銃",
  "説明": "この世界には存在しない技術で作られた、謎の機体",
  "種類": "突進武器",
  "製造情報": {
    "陣営": "一般",
    "型名": "光武（マリア機）",
    "説明": "この世界には存在しない技術で作られた、謎の機体",
    "設計者": "神崎忠義",
    "製造者": "神崎重工"
  },
  "基本性能": {
    "武器倍率": 0.09,
    "攻撃速度": 5.56,
    "エネルギー回復": 72,
    "弾薬数": 30,
    "リロード時間": 1.33,
    "攻撃距離": 25,
    "貫通抵抗": 0,
    "衝撃力": 100,
    "攻撃特性": [
      {
        "飛距離": 30,
        "種類": "弾丸",
        "貫通力": 0.1
      }
    ]
  },
  "専用機性能": {
    "武器倍率": 1,
    "攻撃速度": 3.59,
    "エネルギー回復": 112,
    "弾薬数": 60,
    "リロード時間": 0.33,
    "攻撃距離": 25,
    "貫通抵抗": 0,
    "衝撃力": 100,
    "攻撃特性": [
      {
        "飛距離": 30,
        "種類": "弾丸",
        "貫通力": 0.1
      },
      {
        "飛距離": 300,
        "種類": "弾丸",
        "貫通力": 2
      }
    ]
  }
}
