{
  "名前": "審判の星・投射砲",
  "説明": "理不尽と言えるほどの火力を搭載している。",
  "種類": "投射武器",
  "製造情報": {
    "陣営": "ハイクシアー",
    "型名": "ジャッジメントスター",
    "説明": "聞くところによると、シンシアは最初に一番カッコよくて速いバイクを造ろうとしていたが、スモラに拒否されたらしい。",
    "設計者": "スモラ",
    "製造者": "ジャッジメントスター"
  },
  "基本性能": {
    "武器倍率": 0.68,
    "攻撃速度": 1.01,
    "エネルギー回復": 396,
    "弾薬数": 5,
    "リロード時間": 1.33,
    "攻撃距離": 60,
    "貫通抵抗": 0,
    "衝撃力": 250,
    "攻撃特性": [
      {
        "飛距離": 250,
        "種類": "投射弾",
        "貫通力": 1
      }
    ]
  },
  "専用機性能": {
    "武器倍率": 1.2,
    "攻撃速度": 2.27,
    "エネルギー回復": 120,
    "弾薬数": 6,
    "リロード時間": 0.33,
    "攻撃距離": 60,
    "貫通抵抗": 0,
    "衝撃力": 300,
    "攻撃特性": [
      {
        "飛距離": 300,
        "種類": "投射弾",
        "貫通力": 1
      }
    ]
  }
}
