[
 { "type":"taku4",
   "question":"大陸でもっとも有名な砂漠は？",
   "image":"問題画像/砂漠.jpg",
   "answers":[
     {"string":"ヤハタール"},
     {"string":"ラプール"},
     {"string":"ネブラ"},
     {"string":"ネイルフォード"}
   ]
 }
 ,{"type":"taku4",
   "question":"夏の思い出イベントで獲得できる背景の名前は？",
   "image":"問題画像/パラソルランチ.jpg",
   "answers":[
     {"string":"パラソルランチ"},
     {"string":"パラソルビーチ"},
     {"string":"パラソルパラダイス"},
     {"string":"パラソルまみれ"}
   ]
 }
 ,{"type":"taku4",
   "question":"エスメラルダ専用機のアイテムとしてのセット名は？",
   "image":"問題画像/にゃーセット.jpg",
   "answers":[
     {"string":"にゃーセット"},
     {"string":"にゃんにゃんセット"},
     {"string":"エスメラルダセット"},
     {"string":"わたしは犬派だ"}
   ]
 }
 ,{"type":"taku4",
   "question":"紫にメイド服を着せたときの反応は？",
   "image":"問題画像/紫メイド.jpg",
   "answers":[
     {"string":"三日間任務に出てない"},
     {"string":"自撮りしまくった"},
     {"string":"他の人にも着せようとした"},
     {"string":"踊り狂った"}
   ]
 }
 ,{"type":"taku4icon",
   "question":"ハイクシアー王立学院の生徒募集担当は？",
   "image":"問題画像/ハイクシアー王立学院募集.jpg",
   "answers":[
     {"string":"ユニス","icon":"顔アイコン/ユニス.jpg"},
     {"string":"フリーダ(フレイダ)","icon":"顔アイコン/フリーダ.jpg"},
     {"string":"リレイニ","icon":"顔アイコン/リレイニ.jpg"},
     {"string":"ステラ","icon":"顔アイコン/ステラ.jpg"}
   ]
 }
 ,{"type":"taku4",
   "question":"チャリスが所属するバンドの名前は？",
   "image":"問題画像/チャリスバンド.jpg",
   "answers":[
     {"string":"THETHIREENTH"},
     {"string":"DETHMETAL"},
     {"string":"METALRIDER"},
     {"string":"TREEANDTHREE"}
   ]
 }
 ,{"type":"taku4",
   "question":"THE NECKLYETH TIMESの値段は？",
   "image":"問題画像/ネクリエスタイムズ.jpg",
   "answers":[
     {"string":"$2.50"},
     {"string":"$1.00"},
     {"string":"$7.50"},
     {"string":"プライスレス"}
   ]
 }
 ,{"type":"taku4icon",
   "question":"展示室の交換品に無いものは？",
   "image":"問題画像/展示室.jpg",
   "answers":[
     {"string":"ネジ","icon":"問題画像/ネジ.jpg"},
     {"string":"染付","icon":"問題画像/染付.jpg"},
     {"string":"ネコの貯金箱","icon":"問題画像/ネコの貯金箱.jpg"},
     {"string":"ヨーヨー","icon":"問題画像/ヨーヨー.jpg"}
   ]
 }
 ,{"type":"taku4icon",
   "question":"展示室の望遠鏡の説明に出てくるキャラは？",
   "image":"問題画像/望遠鏡.jpg",
   "answers":[
     {"string":"テア","icon":"顔アイコン/テア.jpg"},
     {"string":"ミロア","icon":"顔アイコン/ミロア.jpg"},
     {"string":"ヴィヴィネ","icon":"顔アイコン/ヴィヴィネ.jpg"},
     {"string":"キーラ","icon":"顔アイコン/キーラ.jpg"}
   ]
 }
 ,{"type":"taku4",
   "question":"地域募集の座標の範囲は？",
   "image":"問題画像/地域募集.jpg",
   "answers":[
     {"string":"縦横-1000から1000"},
     {"string":"縦横-500から500"},
     {"string":"縦横-10000から10000"},
     {"string":"縦横-100000から100000"}
   ]
 }
 ,{"type":"taku4",
   "question":"空白記憶体の最大購入数は？",
   "image":"問題画像/空白記憶体.jpg",
   "answers":[
     {"string":"78回"},
     {"string":"53回"},
     {"string":"102回"},
     {"string":"99回"}
   ]
 }
 ,{"type":"taku4icon",
   "question":"存在しない専用機機体は？",
   "image":"問題画像/専用機図鑑.jpg",
   "answers":[
     {"string":"飛影蝙蝠","icon":"問題画像/飛影蝙蝠.jpg"},
     {"string":"巨頭鯨","icon":"問題画像/巨頭鯨.jpg"},
     {"string":"説得者","icon":"問題画像/説得者.jpg"},
     {"string":"異端審問","icon":"問題画像/異端審問.jpg"}
   ]
 }
 ,{"type":"taku4",
   "question":"蒼鷹シリーズの今の製造者は？",
   "image":"問題画像/蒼鷹軽.jpg",
   "answers":[
     {"string":"デコリーインダストリ"},
     {"string":"オスフィルド工会"},
     {"string":"ヴィラミルインダストリ"},
     {"string":"ブラックアーク"}
   ]
 }
 ,{"type":"taku4",
   "question":"アイスバードシリーズの今の製造者は？",
   "image":"問題画像/アイスバード.jpg",
   "answers":[
     {"string":"ヴィラミルインダストリ"},
     {"string":"デコリーインダストリ"},
     {"string":"オスフィルド工会"},
     {"string":"アイタ工房"}
   ]
 }
 ,{"type":"taku4icon",
   "question":"砂漠の割拠者の設計者は？",
   "image":"問題画像/砂漠の割拠者.jpg",
   "answers":[
     {"string":"シンシア","icon":"顔アイコン/シンシア.jpg"},
     {"string":"スモラ","icon":"顔アイコン/スモラ.jpg"},
     {"string":"チリノ","icon":"顔アイコン/チリノ.jpg"},
     {"string":"ハエラ","icon":"顔アイコン/ハエラ.jpg"}
   ]
 }
 ,{"type":"taku4",
   "question":"平和の使者サブマシンガンの説明は？",
   "image":"問題画像/平和の使者サブマシンガン.jpg",
   "answers":[
     {"string":"クックックッ。"},
     {"string":"ポッポッポッ。"},
     {"string":"フッフッフッ。"},
     {"string":"クックルドゥードゥー。"}
   ]
 }
 ,{"type":"taku4",
   "question":"ホームページの最初の画像でイブリンのぬいぐるみはどうなってる？",
   "image":"問題画像/ホムペ画像.jpg",
   "answers":[
     {"string":"足元のパーツに引っかかってる"},
     {"string":"手に持っている"},
     {"string":"放置されている"},
     {"string":"どこにもいない"}
   ]
 }
 ,{"type":"taku4",
   "question":"「ヘルハピ」の正式名称は？",
   "image":"問題画像/ヘルハピ.jpg",
   "answers":[
     {"string":"ヘルシーアンドハッピーエブリデイ"},
     {"string":"ヘルスアンドハッピーエブリデイ"},
     {"string":"ヘルスアンドヘルシーエブリデイ"},
     {"string":"ヘルシーアンドハッピーエバーデイ"}
   ]
 }
 ,{"type":"taku4",
   "question":"人物図鑑で「ツッコミ役」と書かれてるひとは何人？",
   "image":"問題画像/人物図鑑.jpg",
   "answers":[
     {"string":"1人"},
     {"string":"2人"},
     {"string":"3人"},
     {"string":"4人"}
   ]
 }
 ,{"type":"taku4",
   "question":"この武器の名前は？",
   "image":"問題画像/物理学の聖剣.jpg",
   "answers":[
     {"string":"物理学の聖剣"},
     {"string":"バールのようなもの"},
     {"string":"ギガティッシュ・ザ・バール"},
     {"string":"鈍器"}
   ]
 }
 ,{"type":"taku4",
   "question":"マギーの所属はどこ？",
   "image":"問題画像/マギー.jpg",
   "answers":[
     {"string":"タックチエリア軍"},
     {"string":"アイレタ第一支部"},
     {"string":"リーズエリア軍"},
     {"string":"オーカムエリア軍"}
   ]
 }
 ,{"type":"taku4",
   "question":"ヨランダの賞金ハンター登録番号は？",
   "image":"問題画像/ヨランダ.jpg",
   "answers":[
     {"string":"179号"},
     {"string":"31号"},
     {"string":"6号"},
     {"string":"58号"}
   ]
 }
 ,{"type":"taku4",
   "question":"アウロラのコードネームは？",
   "image":"問題画像/アウロラ.jpg",
   "answers":[
     {"string":"ナース"},
     {"string":"ドクター"},
     {"string":"リペア"},
     {"string":"アイテム係"}
   ]
 }
 ,{"type":"taku4",
   "question":"エスメラルダが個人クエストでやらなかった仕事は？",
   "image":"問題画像/エスメラルダ仕事1.jpg",
   "answers":[
     {"string":"ベルナデットへの連絡"},
     {"string":"サマーフィールドの調停"},
     {"string":"強盗団の撃退"},
     {"string":"α-16の回収"}
   ]
 }
 ,{"type":"taku4",
   "question":"ナコトリスはバソリーのことを何と呼ぶ？",
   "image":"問題画像/バソリー.jpg",
   "answers":[
     {"string":"バソリーちゃん"},
     {"string":"バソ"},
     {"string":"リー"},
     {"string":"バリー"}
   ]
 }
 ,{"type":"taku4",
   "question":"マリーの階級は？",
   "image":"問題画像/マリー.jpg",
   "answers":[
     {"string":"大尉"},
     {"string":"大佐"},
     {"string":"軍曹"},
     {"string":"少将"}
   ]
 }
 ,{"type":"taku4",
   "question":"グレイヴの階級は？",
   "image":"問題画像/グレイヴ.jpg",
   "answers":[
     {"string":"大佐"},
     {"string":"大尉"},
     {"string":"軍曹"},
     {"string":"少将"}
   ]
 }
 ,{"type":"taku4",
   "question":"テアが住んでいたところは？",
   "image":"問題画像/テア.jpg",
   "answers":[
     {"string":"スラム街"},
     {"string":"首都ドリアン"},
     {"string":"メレダ領"},
     {"string":"カルーニヤ地域"}
   ]
 }
 ,{"type":"taku4",
   "question":"ブリーズ・タローが持ち歩かないものは？",
   "image":"問題画像/タロー.jpg",
   "answers":[
     {"string":"大砲"},
     {"string":"トランプ"},
     {"string":"ハト"},
     {"string":"ウサギ"}
   ]
 }
 ,{"type":"taku4",
   "question":"夏イベントの開催地は？",
   "image":"問題画像/夏の思い出.jpg",
   "answers":[
     {"string":"ハイネス"},
     {"string":"サマーフィールド"},
     {"string":"サクストン"},
     {"string":"新城"}
   ]
 }
 ,{"type":"taku4icon",
   "question":"激動の夜明けⅣでイブリンたちが出会うのは？",
   "image":"問題画像/勢力戦前哨.jpg",
   "answers":[
     {"string":"ミロア","icon":"顔アイコン/ミロア.jpg"},
     {"string":"ベルナデット","icon":"顔アイコン/ベルナデット.jpg"},
     {"string":"クリスティーナ","icon":"顔アイコン/クリスティーナ.jpg"},
     {"string":"パッティ","icon":"顔アイコン/パッティ.jpg"}
   ]
 }
 ,{"type":"taku4",
   "question":"勢力戦前哨で海のモンスターが出たと噂された場所は？",
   "image":"問題画像/勢力戦前哨.jpg",
   "answers":[
     {"string":"ヴァイン港"},
     {"string":"サクストン"},
     {"string":"クロベル"},
     {"string":"ジヌンガ港"}
   ]
 }
 ,{"type":"taku4",
   "question":"電子化される前のイブリンの部屋にはディスプレイが何台ある？",
   "image":"問題画像/イブリンの部屋.jpg",
   "answers":[
     {"string":"8台"},
     {"string":"10台"},
     {"string":"6台"},
     {"string":"4台"}
   ]
 }
 ,{"type":"taku4icon",
   "question":"イブリンストーリーで廃墟の調査を依頼したのは？",
   "image":"問題画像/イベントイブリン.jpg",
   "answers":[
     {"string":"ミリーナ","icon":"顔アイコン/ミリーナ.jpg"},
     {"string":"ジェシー","icon":"顔アイコン/ジェシー.jpg"},
     {"string":"クリスティーナ","icon":"顔アイコン/クリスティーナ.jpg"},
     {"string":"モルガン","icon":"顔アイコン/モルガン.jpg"}
   ]
 }
 ,{"type":"taku4",
   "question":"レベリカはモルガンのことを何と呼ぶ？",
   "image":"問題画像/レベリカモルガン.jpg",
   "answers":[
     {"string":"モルガン姉さん"},
     {"string":"モルガン元帥"},
     {"string":"アイレタの星"},
     {"string":"ヘリング元帥"}
   ]
 }
 ,{"type":"taku4",
   "question":"ホイットニーはレベリカのことを何と呼ぶ？",
   "image":"問題画像/ホイットニーレベリカ.jpg",
   "answers":[
     {"string":"レベリカ姉さん"},
     {"string":"レリ"},
     {"string":"戦場の戦乙女"},
     {"string":"レベリカの姉御"}
   ]
 }
 ,{"type":"taku4",
   "question":"イブリンストーリーの舞台となった場所は？",
   "image":"問題画像/イベントイブリン.jpg",
   "answers":[
     {"string":"ラプール山"},
     {"string":"聖殿山"},
     {"string":"帯金火山"},
     {"string":"マウントフジ"}
   ]
 }
 ,{"type":"taku4",
   "question":"ドロレスの姉の名前は？",
   "image":"問題画像/ドロレス.jpg",
   "answers":[
     {"string":"キール"},
     {"string":"キーラ"},
     {"string":"キース"},
     {"string":"キーマ"}
   ]
 }
 ,{"type":"taku4",
   "question":"PN72夜喰の本名は？",
   "image":"問題画像/夜喰スキン.jpg",
   "answers":[
     {"string":"不死川舞"},
     {"string":"不死川唯"},
     {"string":"不死川真希"},
     {"string":"不死川晶"}
   ]
 }
 ,{"type":"taku4",
   "question":"犯罪の都と呼ばれている場所は？",
   "image":"問題画像/ケゲア街.jpg",
   "answers":[
     {"string":"アルチーノ"},
     {"string":"サクストン"},
     {"string":"ハイネス"},
     {"string":"新城"}
   ]
 }
 ,{"type":"taku4",
   "question":"マーグレットを逮捕したのは誰？",
   "image":"問題画像/イベントマーグレット.jpg",
   "answers":[
     {"string":"ソスレス"},
     {"string":"ワラン"},
     {"string":"クライド"},
     {"string":"チャン"}
   ]
 }
 ,{"type":"taku4",
   "question":"マーグレットのフルネームは？",
   "image":"問題画像/マーグレット.jpg",
   "answers":[
     {"string":"マーグレット・フォン・クリスティン"},
     {"string":"マーグレット・フォン・レイ"},
     {"string":"マーグレット・フォン・フロレンティア"},
     {"string":"マーグレット・フォン・レナータ"}
   ]
 }
 ,{"type":"taku4",
   "question":"クロベルの影の最後にレベリカが壊したものとは？",
   "image":"問題画像/クロベルの影.jpg",
   "answers":[
     {"string":"PFP"},
     {"string":"ホワイトレイヴン"},
     {"string":"通信機"},
     {"string":"友情"}
   ]
 }
 ,{"type":"taku4",
   "question":"ケルベロスの首が手に入るのはお金をいくら使ったとき？",
   "image":"問題画像/ケルベロスの首.jpg",
   "answers":[
     {"string":"2800円"},
     {"string":"1200円"},
     {"string":"6000円"},
     {"string":"500円"}
   ]
 }
 ,{"type":"sort4",
   "question":"身長が高い順に並べてください。",
   "tags":["高い","＞","＞","低い"],
   "answers":[
     {"string":"バソリー","icon":"顔アイコン/バソリー.jpg"},
     {"string":"ヴァイオレット","icon":"顔アイコン/ヴァイオレット.jpg"},
     {"string":"九条綾","icon":"顔アイコン/九条綾.jpg"},
     {"string":"スモラ","icon":"顔アイコン/スモラ.jpg"}
   ]
 }
 ,{"type":"sort4",
   "question":"身長が高い順に並べてください。",
   "tags":["高い","＞","＞","低い"],
   "answers":[
     {"string":"イブリン","icon":"顔アイコン/イブリン.jpg"},
     {"string":"ホイットニー","icon":"顔アイコン/ホイットニー.jpg"},
     {"string":"シャディッティ","icon":"顔アイコン/シャディッティ.jpg"},
     {"string":"ドロレス","icon":"顔アイコン/ドロレス.jpg"}
   ]
 }
 ,{"type":"sort4",
   "question":"身長が高い順に並べてください。",
   "tags":["高い","＞","＞","低い"],
   "answers":[
     {"string":"フラビア","icon":"顔アイコン/フラビア.jpg"},
     {"string":"神上園凛","icon":"顔アイコン/神上園凛.jpg"},
     {"string":"小林団子","icon":"顔アイコン/小林団子.jpg"},
     {"string":"紫","icon":"顔アイコン/紫.jpg"}
   ]
 }
 ,{"type":"sort4",
   "question":"誕生日が早い順に並べてください。",
   "tags":["早い","→","→","遅い"],
   "answers":[
     {"string":"マリー","icon":"顔アイコン/マリー.jpg"},
     {"string":"ゾーイ","icon":"顔アイコン/ゾーイ.jpg"},
     {"string":"ヨランダ","icon":"顔アイコン/ヨランダ.jpg"},
     {"string":"チャン","icon":"顔アイコン/チャン.jpg"}
   ]
 }
 ,{"type":"sort4",
   "question":"誕生日が早い順に並べてください。",
   "tags":["早い","→","→","遅い"],
   "answers":[
     {"string":"レンゲル","icon":"顔アイコン/レンゲル.jpg"},
     {"string":"ギャレン","icon":"顔アイコン/ギャレン.jpg"},
     {"string":"ブレイド","icon":"顔アイコン/ブレイド.jpg"},
     {"string":"チャリス","icon":"顔アイコン/チャリス.jpg"}
   ]
 }
 ,{"type":"sort4",
   "question":"誕生日が早い順に並べてください。",
   "tags":["早い","→","→","遅い"],
   "answers":[
     {"string":"エリザベス","icon":"顔アイコン/エリザベス.jpg"},
     {"string":"エロイース","icon":"顔アイコン/エロイース.jpg"},
     {"string":"アレクサ","icon":"顔アイコン/アレクサ.jpg"},
     {"string":"スノーウィー","icon":"顔アイコン/スノーウィー.jpg"}
   ]
 }
 ,{"type":"sort4",
   "question":"必要ポイントが高い順に並べてください。",
   "tags":["高い","＞","＞","安い"],
   "answers":[
     {"string":"フレンドサプライズボックス","icon":"問題画像/フレンドサプライズボックス.jpg"},
     {"string":"フレンドコイン箱","icon":"問題画像/フレンドコイン箱.jpg"},
     {"string":"フレンドパーツ箱","icon":"問題画像/フレンドパーツ箱.jpg"},
     {"string":"フレンドベースカー補給箱","icon":"問題画像/フレンドベースカー補給箱.jpg"}
   ]
 }
 ,{"type":"sort4",
   "question":"称号をランクが高い順に並べてください。",
   "tags":["高い","＞","＞","低い"],
   "answers":[
     {"string":"奮励の証","icon":"問題画像/称号奮励の証.jpg"},
     {"string":"努力の証","icon":"問題画像/称号努力の証.jpg"},
     {"string":"忍耐の証","icon":"問題画像/称号忍耐の証.jpg"},
     {"string":"参加の証","icon":"問題画像/称号参加の証.jpg"}
   ]
 }
 ,{"type":"sort4",
   "question":"必要試練コインが少ない順に並べてください。(1個の値段)",
   "tags":["少ない","＜","＜","多い"],
   "answers":[
     {"string":"スーパー擬態合金","icon":"問題画像/スーパー擬態合金.jpg"},
     {"string":"NR動力装置","icon":"問題画像/NR動力装置.jpg"},
     {"string":"OSUAモジュール","icon":"問題画像/OSUAモジュール.jpg"},
     {"string":"特級昇進証","icon":"問題画像/特級昇進証.jpg"}
   ]
 }
 ,{"type":"sort4",
   "question":"物資備蓄のボス登場が早い順に並べてください。",
   "tags":["早い","→","→","遅い"],
   "answers":[
     {"string":"エスメラルダ","icon":"顔アイコン/エスメラルダ.jpg"},
     {"string":"イーレヒース","icon":"顔アイコン/PN26イーレヒース.jpg"},
     {"string":"ベルフォード","icon":"顔アイコン/ベルフォード.jpg"},
     {"string":"ヴァイオレット","icon":"顔アイコン/ヴァイオレット.jpg"}
   ]
 }
 ,{"type":"sort4",
   "question":"イブリンストーリー順に並び変えてください。",
   "tags":["先","→","→","後"],
   "answers":[
     {"string":"ロスト・ページ","icon":"問題画像/イブリンストーリー2.jpg"},
     {"string":"超我","icon":"問題画像/イブリンストーリー3.jpg"},
     {"string":"記憶の本棚","icon":"問題画像/イブリンストーリー4.jpg"},
     {"string":"本我","icon":"問題画像/イブリンストーリー5.jpg"}
   ]
 }
 ,{"type":"sort4",
   "question":"ショップアイテムの売品を安いもの順に並べてください。",
   "tags":["安い","＜","＜","高い"],
   "answers":[
     {"string":"入門作戦理論","icon":"問題画像/入門作戦理論.jpg"},
     {"string":"通常開発パーツ","icon":"問題画像/通常開発パーツ.jpg"},
     {"string":"コイン","icon":"問題画像/ショップコイン.jpg"},
     {"string":"システム更新","icon":"問題画像/システム更新.jpg"}
   ]
 }
 ,{"type":"classify2",
   "question":"天性が敏捷のキャラとそれ以外に分けてください。",
   "answers":{
     "敏捷":[
       {"string":"神上園凛","icon":"顔アイコン/神上園凛.jpg"},
       {"string":"マリー","icon":"顔アイコン/マリー.jpg"},
       {"string":"アドリエンヌ","icon":"顔アイコン/アドリエンヌ.jpg"}
     ],
     "それ以外":[
       {"string":"ヨランダ","icon":"顔アイコン/ヨランダ.jpg"},
       {"string":"オードリー","icon":"顔アイコン/オードリー.jpg"},
       {"string":"ミシェリア","icon":"顔アイコン/ミシェリア.jpg"}
     ]
   }
 }
 ,{"type":"classify2",
   "question":"天性が知性のキャラとそれ以外に分けてください。",
   "answers":{
     "知性":[
       {"string":"チャン","icon":"顔アイコン/チャン.jpg"},
       {"string":"ソルヴェイグ","icon":"顔アイコン/ソルヴェイグ.jpg"},
       {"string":"フラビア","icon":"顔アイコン/フラビア.jpg"}
     ],
     "それ以外":[
       {"string":"ノーヴァ","icon":"顔アイコン/ノーヴァ.jpg"},
       {"string":"グレイヴ","icon":"顔アイコン/グレイヴ.jpg"},
       {"string":"マギー","icon":"顔アイコン/マギー.jpg"}
     ]
   }
 }
 ,{"type":"classify2",
   "question":"天性が体質のキャラとそれ以外に分けてください。",
   "answers":{
     "体質":[
       {"string":"シャディッティ","icon":"顔アイコン/シャディッティ.jpg"},
       {"string":"ブルターニ","icon":"顔アイコン/ブルターニ.jpg"},
       {"string":"ゾーイ","icon":"顔アイコン/ゾーイ.jpg"}
     ],
     "それ以外":[
       {"string":"マーグレット","icon":"顔アイコン/マーグレット.jpg"},
       {"string":"フェヴィア","icon":"顔アイコン/フェヴィア.jpg"},
       {"string":"ホイットニー","icon":"顔アイコン/ホイットニー.jpg"}
     ]
   }
 }
 ,{"type":"classify2",
   "question":"天性が感情のキャラとそれ以外に分けてください。",
   "answers":{
     "感情":[
       {"string":"ロクサーヌ","icon":"顔アイコン/ロクサーヌ.jpg"},
       {"string":"シャコガイ","icon":"顔アイコン/シャコガイ.jpg"},
       {"string":"チャリス","icon":"顔アイコン/チャリス.jpg"}
     ],
     "それ以外":[
       {"string":"エイダ","icon":"顔アイコン/エイダ.jpg"},
       {"string":"スウィーティー","icon":"顔アイコン/スウィーティー.jpg"},
       {"string":"ヘレーナ","icon":"顔アイコン/ヘレーナ.jpg"}
     ]
   }
 }
 ,{"type":"classify2",
   "question":"天性が製造のキャラとそれ以外に分けてください。",
   "answers":{
     "製造":[
       {"string":"ヴァイオレット","icon":"顔アイコン/ヴァイオレット.jpg"},
       {"string":"シェール","icon":"顔アイコン/シェール.jpg"},
       {"string":"メイメイ","icon":"顔アイコン/メイメイ.jpg"}
     ],
     "それ以外":[
       {"string":"ニッジー","icon":"顔アイコン/ニッジー.jpg"},
       {"string":"ミリーナ","icon":"顔アイコン/ミリーナ.jpg"},
       {"string":"ナターシャ","icon":"顔アイコン/ナターシャ.jpg"}
     ]
   }
 }
 ,{"type":"classify2",
   "question":"血液型ＡとＢに分けてください。",
   "answers":{
     "Ａ":[
       {"string":"アウロラ","icon":"顔アイコン/アウロラ.jpg"},
       {"string":"エスメラルダ","icon":"顔アイコン/エスメラルダ.jpg"},
       {"string":"テア","icon":"顔アイコン/テア.jpg"}
     ],
     "Ｂ":[
       {"string":"ミリーナ","icon":"顔アイコン/ミリーナ.jpg"},
       {"string":"ネプリム","icon":"顔アイコン/ネプリム.jpg"},
       {"string":"フラビア","icon":"顔アイコン/フラビア.jpg"}
     ]
   }
 }
 ,{"type":"classify2",
   "question":"血液型ABとOに分けてください。",
   "answers":{
     "AB":[
       {"string":"ホイットニー","icon":"顔アイコン/ホイットニー.jpg"},
       {"string":"鬼影灯","icon":"顔アイコン/鬼影灯.jpg"},
       {"string":"ミロア","icon":"顔アイコン/ミロア.jpg"}
     ],
     "ｏ":[
       {"string":"フーラ","icon":"顔アイコン/フーラ.jpg"},
       {"string":"オードリー","icon":"顔アイコン/オードリー.jpg"},
       {"string":"フェニックス","icon":"顔アイコン/フェニックス.jpg"}
     ]
   }
 }
 ,{"type":"classify2",
   "question":"血液型AとOに分けてください。",
   "answers":{
     "Ａ":[
       {"string":"レベリカ","icon":"顔アイコン/レベリカ.jpg"},
       {"string":"ブレイド","icon":"顔アイコン/ブレイド.jpg"},
       {"string":"マルマ","icon":"顔アイコン/マルマ.jpg"}
     ],
     "ｏ":[
       {"string":"紫","icon":"顔アイコン/紫.jpg"},
       {"string":"リンベル","icon":"顔アイコン/リンベル.jpg"},
       {"string":"チリノ","icon":"顔アイコン/チリノ.jpg"}
     ]
   }
 }
 ,{"type":"classify2",
   "question":"血液型BとABに分けてください。",
   "answers":{
     "Ｂ":[
       {"string":"メイメイ","icon":"顔アイコン/メイメイ.jpg"},
       {"string":"ヴィオラ","icon":"顔アイコン/ヴィオラ.jpg"},
       {"string":"シュミリ","icon":"顔アイコン/シュミリ.jpg"}
     ],
     "AB":[
       {"string":"エリザベス","icon":"顔アイコン/エリザベス.jpg"},
       {"string":"ジェシー","icon":"顔アイコン/ジェシー.jpg"},
       {"string":"フェヴィア","icon":"顔アイコン/フェヴィア.jpg"}
     ]
   }
 }
 ,{"type":"classify2",
   "question":"突進武器とマシンガン武器に分けてください。",
   "answers":{
     "突進武器":[
       {"string":"スウィーティー","icon":"顔アイコン/スウィーティー.jpg"},
       {"string":"チャン","icon":"顔アイコン/チャン.jpg"},
       {"string":"マリー","icon":"顔アイコン/マリー.jpg"}
     ],
     "マシンガン武器":[
       {"string":"メイメイ","icon":"顔アイコン/メイメイ.jpg"},
       {"string":"ローラー","icon":"顔アイコン/ローラー.jpg"},
       {"string":"バソリー","icon":"顔アイコン/バソリー.jpg"}
     ]
   }
 }
 ,{"type":"classify2",
   "question":"突撃武器と強襲武器に分けてください。",
   "answers":{
     "突撃武器":[
       {"string":"マギー","icon":"顔アイコン/マギー.jpg"},
       {"string":"テア","icon":"顔アイコン/テア.jpg"},
       {"string":"鬼影灯","icon":"顔アイコン/鬼影灯.jpg"}
     ],
     "強襲武器":[
       {"string":"オードリー","icon":"顔アイコン/バソリー.jpg"},
       {"string":"アドリエンヌ","icon":"顔アイコン/アドリエンヌ.jpg"},
       {"string":"フェニックス","icon":"顔アイコン/フェニックス.jpg"}
     ]
   }
 }
 ,{"type":"classify2",
   "question":"防壁武器と片手武器に分けてください。",
   "answers":{
     "防壁武器":[
       {"string":"ホイットニー","icon":"顔アイコン/ホイットニー.jpg"},
       {"string":"ブルターニ","icon":"顔アイコン/ブルターニ.jpg"},
       {"string":"マルマ","icon":"顔アイコン/マルマ.jpg"}
     ],
     "片手武器":[
       {"string":"アウロラ","icon":"顔アイコン/アウロラ.jpg"},
       {"string":"フーラ","icon":"顔アイコン/フーラ.jpg"},
       {"string":"ネプリム","icon":"顔アイコン/ネプリム.jpg"}
     ]
   }
 }
 ,{"type":"classify2",
   "question":"展示室ヘルプの団長Aの陳列棚に入っているものを分けてください。",
   "answers":{
     "入ってる":[
       {"string":"人形","icon":"問題画像/人形.jpg"},
       {"string":"クマのぬいぐるみ","icon":"問題画像/クマのぬいぐるみ.jpg"},
       {"string":"タロットカード","icon":"問題画像/タロットカード.jpg"}
     ],
     "入ってない":[
       {"string":"水着の販売ポスター","icon":"問題画像/水着の販売ポスター.jpg"},
       {"string":"イブリンのゲーム機","icon":"問題画像/イブリンのゲーム機.jpg"},
       {"string":"シュミリの腕","icon":"問題画像/シュミリの腕.jpg"}
     ]
   }
 }
 ,{"type":"combi3",
   "question":"砂漠の嵐の型名称と機体を組み合わせてください。",
   "answers":{
     "水流":{"string":"砂漠の嵐軽","icon":"問題画像/砂漠の嵐軽.jpg"},
     "沼沢":{"string":"砂漠の嵐中","icon":"問題画像/砂漠の嵐中.jpg"},
     "嵐":{"string":"砂漠の嵐重","icon":"問題画像/砂漠の嵐重.jpg"}
   }
 }
 ,{"type":"combi3",
   "question":"蒼鷹の型名称と機体を組み合わせてください。",
   "answers":{
     "LV4":{"string":"蒼鷹軽","icon":"問題画像/蒼鷹軽.jpg"},
     "LV3":{"string":"蒼鷹中","icon":"問題画像/蒼鷹中.jpg"},
     "LV2":{"string":"蒼鷹重","icon":"問題画像/蒼鷹重.jpg"}
   }
 }
 ,{"type":"combi3",
   "question":"審判者の型名称と機体を組み合わせてください。",
   "answers":{
     "エリート":{"string":"/審判者軽","icon":"問題画像/審判者軽.jpg"},
     "ナイト":{"string":"/審判者中","icon":"問題画像/審判者中.jpg"},
     "ビショップ":{"string":"/審判者重","icon":"問題画像/審判者重.jpg"}
   }
 }
 ,{"type":"combi3",
   "question":"タイシアのスキルを正しく組み合わせてください。",
   "answers":{
     "自律":{"string":"タイシア自律","icon":"問題画像/タイシア自律.jpg"},
     "心眼":{"string":"タイシア心眼","icon":"問題画像/タイシア心眼.jpg"},
     "一心不乱":{"string":"タイシア一心不乱","icon":"問題画像/タイシア一心不乱.jpg"}
   }
 }
 ,{"type":"combi3",
   "question":"ノーヴァのスキルを正しく組み合わせてください。",
   "answers":{
     "分裂？":{"string":"ノーヴァ分裂？","icon":"問題画像/ノーヴァ分裂？.jpg"},
     "未知生物？":{"string":"ノーヴァ未知生物？","icon":"問題画像/ノーヴァ未知生物？.jpg"},
     "触り禁止？":{"string":"ノーヴァ触り禁止？","icon":"問題画像/ノーヴァ触り禁止？.jpg"}
   }
 }
 ,{"type":"combi3",
   "question":"エスメラルダのスキルを正しく組み合わせてください。",
   "answers":{
     "激励":{"string":"エスメラルダ激励","icon":"問題画像/エスメラルダ激励.jpg"},
     "攻撃強化":{"string":"エスメラルダ攻撃強化","icon":"問題画像/エスメラルダ攻撃強化.jpg"},
     "不屈の意思":{"string":"エスメラルダ不屈の意思","icon":"問題画像/エスメラルダ不屈の意思.jpg"}
   }
 }
 ,{"type":"combi3",
   "question":"マーグレットのスキルを正しく組み合わせてください。",
   "answers":{
     "審判の鉄槌":{"string":"マーグレット審判の鉄槌","icon":"問題画像/マーグレット審判の鉄槌.jpg"},
     "永遠なる信仰":{"string":"マーグレット永遠なる信仰","icon":"問題画像/マーグレット永遠なる信仰.jpg"},
     "揺るぎなき信仰":{"string":"マーグレット揺るぎなき信仰","icon":"問題画像/マーグレット揺るぎなき信仰.jpg"}
   }
 }
 ,{"type":"combi3",
   "question":"メイメイのスキルを正しく組み合わせてください。",
   "answers":{
     "命中上昇":{"string":"メイメイ命中上昇","icon":"問題画像/メイメイ命中上昇.jpg"},
     "衰弱アタック":{"string":"メイメイ衰弱アタック","icon":"問題画像/メイメイ衰弱アタック.jpg"},
     "戦闘強化":{"string":"メイメイ戦闘強化","icon":"問題画像/メイメイ戦闘強化.jpg"}
   }
 }
 ,{"type":"combi3",
   "question":"グレイヴのスキルを正しく組み合わせてください。",
   "answers":{
     "攻撃強化":{"string":"グレイヴ攻撃強化","icon":"問題画像/グレイヴ攻撃強化.jpg"},
     "速度＋":{"string":"グレイヴ速度＋","icon":"問題画像/グレイヴ速度＋.jpg"},
     "会心強化":{"string":"グレイヴ会心強化","icon":"問題画像/グレイヴ会心強化.jpg"}
   }
 }
 ,{"type":"combi3",
   "question":"タイシアの後方スキルを正しく組み合わせてください。",
   "answers":{
     "知性":{"string":"警察犬の嗅覚"},
     "製造":{"string":"ゴールドティガー"},
     "感情":{"string":"戦闘研究員"}
   }
 }
 ,{"type":"combi3",
   "question":"ノーヴァの後方スキルを正しく組み合わせてください。",
   "answers":{
     "知性":{"string":"乗り物研究"},
     "敏捷":{"string":"マーメイド"},
     "感情":{"string":"ネブラ井戸掘り"}
   }
 }
 ,{"type":"combi3",
   "question":"チャンの後方スキルを正しく組み合わせてください。",
   "answers":{
     "知性":{"string":"アイレタ狂騒者"},
     "体質":{"string":"警備員"},
     "感情":{"string":"荒野の掘削機"}
   }
 }
 ,{"type":"combi3",
   "question":"ソルヴェイグの後方スキルを正しく組み合わせてください。",
   "answers":{
     "知性":{"string":"修理の達人"},
     "体質":{"string":"食材名手"},
     "感情":{"string":"ケゲア守銭奴"}
   }
 }
 ,{"type":"combi3",
   "question":"ナターシャの後方スキルを正しく組み合わせてください。",
   "answers":{
     "製造":{"string":"アイレタ賞金ハンター"},
     "敏捷":{"string":"グルメ評論家"},
     "感情":{"string":"超金濾過"}
   }
 }
 ,{"type":"combi3",
   "question":"イブリンの後方スキルを正しく組み合わせてください。",
   "answers":{
     "知性":{"string":"イブリンの才能"},
     "製造":{"string":"ゲーマー"},
     "感情":{"string":"効率的サボリ術"}
   }
 }
 ,{"type":"combi3",
   "question":"週間パックの値段と商品を正しく組み合わせてください。",
   "answers":{
     "250クリスタル":{"string":"好感度パック・華"},
     "150クリスタル":{"string":"好感度パック・咲"},
     "60クリスタル":{"string":"好感度パック・芽"}
   }
 }
 ,{"type":"combi3",
   "question":"収集パーツの称号正しく組み合わせてください。",
   "answers":{
     "武器":{"string":"戦闘民族","icon":"問題画像/称号戦闘民族.png"},
     "脚部":{"string":"ヘルハピ","icon":"問題画像/称号ヘルハピ.png"},
     "背部":{"string":"魔法少女","icon":"問題画像/称号魔法少女.png"}
   }
 }
 ,{"type":"place",
   "question":"新城はどこ？",
   "image":"問題画像/地形アイレタ.jpg",
   "answers":[
    {"x":436,"y":49},
    {"x":57,"y":105},
    {"x":193,"y":313},
    {"x":441,"y":312}
   ]
 }
 ,{"type":"place",
   "question":"ドリアンはどこ？",
   "image":"問題画像/地形ケゲア.jpg",
   "answers":[
    {"x":186,"y":233},
    {"x":367,"y":276},
    {"x":260,"y":388},
    {"x":122,"y":320}
   ]
 }
 ,{"type":"place",
   "question":"リーズはどこ？",
   "image":"問題画像/地形アイレタ.jpg",
   "answers":[
    {"x":312,"y":222},
    {"x":60,"y":359},
    {"x":68,"y":70},
    {"x":302,"y":380}
   ]
 }
 ,{"type":"place",
   "question":"ヘルシンはどこ？",
   "image":"問題画像/地形ケゲア.jpg",
   "answers":[
    {"x":131,"y":174},
    {"x":447,"y":187},
    {"x":63,"y":347},
    {"x":265,"y":244}
   ]
 }
 ,{"type":"place",
   "question":"アリアックはどこ？",
   "image":"問題画像/地形ハイクシアー.jpg",
   "answers":[
    {"x":305,"y":224},
    {"x":481,"y":260},
    {"x":72,"y":227},
    {"x":293,"y":356}
   ]
 }
 ,{"type":"place",
   "question":"マークティアはどこ？",
   "image":"問題画像/地形ハイクシアー.jpg",
   "answers":[
    {"x":475,"y":396},
    {"x":124,"y":116},
    {"x":103,"y":388},
    {"x":422,"y":107}
   ]
 }
 ,{"type":"place",
   "question":"アルチーノはどこ？",
   "image":"問題画像/地形ケゲア.jpg",
   "answers":[
    {"x":128,"y":346},
    {"x":70,"y":254},
    {"x":163,"y":56},
    {"x":411,"y":396}
   ]
 }
 ,{"type":"taku4icon",
   "question":"これは誰の物？",
   "image":"問題画像/【NEW】スノーウィ小物_1.png",
   "answers":[
     {"string":"スノーウィー","icon":"顔アイコン/スノーウィー.jpg"},
     {"string":"ナターシャ","icon":"顔アイコン/ナターシャ.jpg"},
     {"string":"シーメ","icon":"顔アイコン/シーメ.jpg"},
     {"string":"リンベル","icon":"顔アイコン/リンベル.jpg"}
   ]
 }
 ,{"type":"taku4icon",
   "question":"これは誰の物？",
   "image":"問題画像/【NEW】ドロレス小物_1.png",
   "answers":[
     {"string":"ドロレス","icon":"顔アイコン/ドロレス.jpg"},
     {"string":"紫","icon":"顔アイコン/紫.jpg"},
     {"string":"ロクサーヌ","icon":"顔アイコン/ロクサーヌ.jpg"},
     {"string":"ヴィヴィネ","icon":"顔アイコン/ヴィヴィネ.jpg"}
   ]
 }
 ,{"type":"taku4icon",
   "question":"これは誰の物？",
   "image":"問題画像/【NEW】フラビア小物_1.png",
   "answers":[
     {"string":"フラビア","icon":"顔アイコン/フラビア.jpg"},
     {"string":"神上園凛","icon":"顔アイコン/神上園凛.jpg"},
     {"string":"九条綾","icon":"顔アイコン/九条綾.jpg"},
     {"string":"タイシア","icon":"顔アイコン/タイシア.jpg"}
   ]
 }
 ,{"type":"taku4icon",
   "question":"これは誰の物？",
   "image":"問題画像/【NEW】華蘭小物_1.png",
   "answers":[
     {"string":"華蘭","icon":"顔アイコン/華蘭.jpg"},
     {"string":"ポーラ","icon":"顔アイコン/ポーラ.jpg"},
     {"string":"ポーラー","icon":"顔アイコン/ポーラー.jpg"},
     {"string":"アイタ","icon":"顔アイコン/アイタ.jpg"}
   ]
 }
 ,{"type":"taku4icon",
   "question":"これは誰の物？",
   "image":"問題画像/【NEW】凛ちゃん小物_4.png",
   "answers":[
     {"string":"神上園凛","icon":"顔アイコン/神上園凛.jpg"},
     {"string":"フラビア","icon":"顔アイコン/フラビア.jpg"},
     {"string":"九条綾","icon":"顔アイコン/九条綾.jpg"},
     {"string":"タイシア","icon":"顔アイコン/タイシア.jpg"}
   ]
 }
 ,{"type":"imagepanel",
   "question":"これは誰？",
   "image":"キャラ画像/PN26イーレヒース.jpg",
   "answers":[
     {"string":"PN26イーレヒース","icon":"顔アイコン/PN26イーレヒース.jpg"},
     {"string":"PN72夜喰","icon":"顔アイコン/PN72夜喰.jpg"},
     {"string":"PN99","icon":"顔アイコン/PN99.jpg"},
     {"string":"ドロレス","icon":"顔アイコン/ドロレス.jpg"}
   ]
 }
 ,{"type":"imagefilter",
   "question":"これは誰？",
   "image":"キャラ画像/α-16.jpg",
   "answers":[
     {"string":"α-16","icon":"顔アイコン/α-16.jpg"},
     {"string":"ヴィヴィネ","icon":"顔アイコン/ヴィヴィネ.jpg"},
     {"string":"イブリン","icon":"顔アイコン/イブリン.jpg"},
     {"string":"アリエル","icon":"顔アイコン/アリエル.jpg"}
   ]
 }
 ,{"type":"imageskew",
   "question":"これは誰？",
   "image":"キャラ画像/アイタ.jpg",
   "answers":[
     {"string":"アイタ","icon":"顔アイコン/アイタ.jpg"},
     {"string":"華蘭","icon":"顔アイコン/華蘭.jpg"},
     {"string":"ポーラ","icon":"顔アイコン/ポーラ.jpg"},
     {"string":"チリノ","icon":"顔アイコン/チリノ.jpg"}
   ]
 }
 ,{"type":"imagezoom",
   "question":"これは誰？",
   "image":"キャラ画像/アウロラ.jpg",
   "answers":[
     {"string":"アウロラ","icon":"顔アイコン/アウロラ.jpg"},
     {"string":"リー","icon":"顔アイコン/リー.jpg"},
     {"string":"アリエル","icon":"顔アイコン/アリエル.jpg"},
     {"string":"リンベル","icon":"顔アイコン/リンベル.jpg"}
   ]
 }
 ,{"type":"imagepanel",
   "question":"これは誰？",
   "image":"キャラ画像/アドリエンヌ.jpg",
   "answers":[
     {"string":"アドリエンヌ","icon":"顔アイコン/アドリエンヌ.jpg"},
     {"string":"タイシア","icon":"顔アイコン/タイシア.jpg"},
     {"string":"神上園凛","icon":"顔アイコン/神上園凛.jpg"},
     {"string":"フラビア","icon":"顔アイコン/フラビア.jpg"}
   ]
 }
 ,{"type":"imagefilter",
   "question":"これは誰？",
   "image":"キャラ画像/アリエル.jpg",
   "answers":[
     {"string":"アリエル","icon":"顔アイコン/アリエル.jpg"},
     {"string":"α-16","icon":"顔アイコン/α-16.jpg"},
     {"string":"ニッジー","icon":"顔アイコン/ニッジー.jpg"},
     {"string":"リンベル","icon":"顔アイコン/リンベル.jpg"}
   ]
 }
 ,{"type":"imageskew",
   "question":"これは誰？",
   "image":"キャラ画像/アンバー.jpg",
   "answers":[
     {"string":"アンバー","icon":"顔アイコン/アンバー.jpg"},
     {"string":"シャディッティ","icon":"顔アイコン/シャディッティ.jpg"},
     {"string":"マリー","icon":"顔アイコン/マリー.jpg"},
     {"string":"ミロア","icon":"顔アイコン/ミロア.jpg"}
   ]
 }
 ,{"type":"imagezoom",
   "question":"これは誰？",
   "image":"キャラ画像/イブリン.jpg",
   "answers":[
     {"string":"イブリン","icon":"顔アイコン/イブリン.jpg"},
     {"string":"ヴェロニカ","icon":"顔アイコン/ヴェロニカ.jpg"},
     {"string":"レベリカ","icon":"顔アイコン/レベリカ.jpg"},
     {"string":"クリスティーナ","icon":"顔アイコン/クリスティーナ.jpg"}
   ]
 }
 ,{"type":"imagepanel",
   "question":"これは誰？",
   "image":"キャラ画像/ヴィヴィネ.jpg",
   "answers":[
     {"string":"ヴィヴィネ","icon":"顔アイコン/ヴィヴィネ.jpg"},
     {"string":"アドリエンヌ","icon":"顔アイコン/アドリエンヌ.jpg"},
     {"string":"ニッジー","icon":"顔アイコン/ニッジー.jpg"},
     {"string":"ゾーイ","icon":"顔アイコン/ゾーイ.jpg"}
   ]
 }
 ,{"type":"imagefilter",
   "question":"これは誰？",
   "image":"キャラ画像/ヴィオラ.jpg",
   "answers":[
     {"string":"ヴィオラ","icon":"顔アイコン/ヴィオラ.jpg"},
     {"string":"グレイヴ","icon":"顔アイコン/グレイヴ.jpg"},
     {"string":"紫","icon":"顔アイコン/紫.jpg"},
     {"string":"ギャレン","icon":"顔アイコン/ギャレン.jpg"}
   ]
 }
 ,{"type":"imageskew",
   "question":"これは誰？",
   "image":"キャラ画像/ヴェロニカ.jpg",
   "answers":[
     {"string":"ヴェロニカ","icon":"顔アイコン/ヴェロニカ.jpg"},
     {"string":"シーメ","icon":"顔アイコン/シーメ.jpg"},
     {"string":"ネプリム","icon":"顔アイコン/ネプリム.jpg"},
     {"string":"キーラ","icon":"顔アイコン/キーラ.jpg"}
   ]
 }
 ,{"type":"imagezoom",
   "question":"これは誰？",
   "image":"キャラ画像/エイダ.jpg",
   "answers":[
     {"string":"エイダ","icon":"顔アイコン/エイダ.jpg"},
     {"string":"リー","icon":"顔アイコン/リー.jpg"},
     {"string":"アウロラ","icon":"顔アイコン/アウロラ.jpg"},
     {"string":"ポーラ","icon":"顔アイコン/ポーラ.jpg"}
   ]
 }
 ,{"type":"imagepanel",
   "question":"これは誰？",
   "image":"キャラ画像/エスメラルダ.jpg",
   "answers":[
     {"string":"エスメラルダ","icon":"顔アイコン/エスメラルダ.jpg"},
     {"string":"ヴェロニカ","icon":"顔アイコン/ヴェロニカ.jpg"},
     {"string":"ミロア","icon":"顔アイコン/ミロア.jpg"},
     {"string":"スウィーティー","icon":"顔アイコン/スウィーティー.jpg"}
   ]
 }
 ,{"type":"imagefilter",
   "question":"これは誰？",
   "image":"キャラ画像/エッギーペッギー.jpg",
   "answers":[
     {"string":"エッギーペッギー","icon":"顔アイコン/エッギーペッギー.jpg"},
     {"string":"ゾーイ","icon":"顔アイコン/ゾーイ.jpg"},
     {"string":"2233","icon":"顔アイコン/2233.jpg"},
     {"string":"マギー","icon":"顔アイコン/マギー.jpg"}
   ]
 }
 ,{"type":"imageskew",
   "question":"これは誰？",
   "image":"キャラ画像/オイフェ.jpg",
   "answers":[
     {"string":"オイフェ","icon":"顔アイコン/オイフェ.jpg"},
     {"string":"アレクサ","icon":"顔アイコン/アレクサ.jpg"},
     {"string":"チリノ","icon":"顔アイコン/チリノ.jpg"},
     {"string":"クリスティーナ","icon":"顔アイコン/クリスティーナ.jpg"}
   ]
 }
 ,{"type":"imagezoom",
   "question":"これは誰？",
   "image":"キャラ画像/オードリー.jpg",
   "answers":[
     {"string":"オードリー","icon":"顔アイコン/オードリー.jpg"},
     {"string":"バソリー","icon":"顔アイコン/バソリー.jpg"},
     {"string":"ヘレーナ","icon":"顔アイコン/ヘレーナ.jpg"},
     {"string":"マルマ","icon":"顔アイコン/マルマ.jpg"}
   ]
 }
 ,{"type":"imagepanel",
   "question":"これは誰？",
   "image":"キャラ画像/キーラ.jpg",
   "answers":[
     {"string":"キーラ","icon":"顔アイコン/キーラ.jpg"},
     {"string":"シーメ","icon":"顔アイコン/シーメ.jpg"},
     {"string":"ポーラ","icon":"顔アイコン/ポーラ.jpg"},
     {"string":"紫","icon":"顔アイコン/紫.jpg"}
   ]
 }
 ,{"type":"imagefilter",
   "question":"これは誰？",
   "image":"キャラ画像/ギャレン.jpg",
   "answers":[
     {"string":"ギャレン","icon":"顔アイコン/ギャレン.jpg"},
     {"string":"グレイヴ","icon":"顔アイコン/グレイヴ.jpg"},
     {"string":"紫","icon":"顔アイコン/紫.jpg"},
     {"string":"シンシア","icon":"顔アイコン/シンシア.jpg"}
   ]
 }
 ,{"type":"imageskew",
   "question":"これは誰？",
   "image":"キャラ画像/クリスティーナ.jpg",
   "answers":[
     {"string":"クリスティーナ","icon":"顔アイコン/クリスティーナ.jpg"},
     {"string":"オードリー","icon":"顔アイコン/オードリー.jpg"},
     {"string":"オイフェ","icon":"顔アイコン/オイフェ.jpg"},
     {"string":"ロクサーヌ","icon":"顔アイコン/ロクサーヌ.jpg"}
   ]
 }
 ,{"type":"imagezoom",
   "question":"これは誰？",
   "image":"キャラ画像/グレイヴ.jpg",
   "answers":[
     {"string":"グレイヴ","icon":"顔アイコン/グレイヴ.jpg"},
     {"string":"アイタ","icon":"顔アイコン/アイタ.jpg"},
     {"string":"ジェシー","icon":"顔アイコン/ジェシー.jpg"},
     {"string":"ナターシャ","icon":"顔アイコン/ナターシャ.jpg"}
   ]
 }
 ,{"type":"imagepanel",
   "question":"これは誰？",
   "image":"キャラ画像/コーレリア.jpg",
   "answers":[
     {"string":"コーレリア","icon":"顔アイコン/コーレリア.jpg"},
     {"string":"マーグレット","icon":"顔アイコン/マーグレット.jpg"},
     {"string":"アドリエンヌ","icon":"顔アイコン/アドリエンヌ.jpg"},
     {"string":"フェニックス","icon":"顔アイコン/フェニックス.jpg"}
   ]
 }
 ,{"type":"imagefilter",
   "question":"これは誰？",
   "image":"キャラ画像/シーメ.jpg",
   "answers":[
     {"string":"シーメ","icon":"顔アイコン/シーメ.jpg"},
     {"string":"ヴェロニカ","icon":"顔アイコン/ヴェロニカ.jpg"},
     {"string":"エイダ","icon":"顔アイコン/エイダ.jpg"},
     {"string":"テア","icon":"顔アイコン/テア.jpg"}
   ]
 }
 ,{"type":"imageskew",
   "question":"これは誰？",
   "image":"キャラ画像/シェール.jpg",
   "answers":[
     {"string":"シェール","icon":"顔アイコン/シェール.jpg"},
     {"string":"スウィーティー","icon":"顔アイコン/スウィーティー.jpg"},
     {"string":"メイメイ","icon":"顔アイコン/メイメイ.jpg"},
     {"string":"ローラー","icon":"顔アイコン/ローラー.jpg"}
   ]
 }
 ,{"type":"imagezoom",
   "question":"これは誰？",
   "image":"キャラ画像/ジェシー.jpg",
   "answers":[
     {"string":"ジェシー","icon":"顔アイコン/ジェシー.jpg"},
     {"string":"リー","icon":"顔アイコン/リー.jpg"},
     {"string":"レベリカ","icon":"顔アイコン/レベリカ.jpg"},
     {"string":"ヨランダ","icon":"顔アイコン/ヨランダ.jpg"}
   ]
 }
 ,{"type":"imagepanel",
   "question":"これは誰？",
   "image":"キャラ画像/ジャスミン.jpg",
   "answers":[
     {"string":"ジャスミン","icon":"顔アイコン/ジャスミン.jpg"},
     {"string":"マリー","icon":"顔アイコン/マリー.jpg"},
     {"string":"マギー","icon":"顔アイコン/マギー.jpg"},
     {"string":"シャディッティ","icon":"顔アイコン/シャディッティ.jpg"}
   ]
 }
 ,{"type":"imagefilter",
   "question":"これは誰？",
   "image":"キャラ画像/シャディッティ.jpg",
   "answers":[
     {"string":"シャディッティ","icon":"顔アイコン/シャディッティ.jpg"},
     {"string":"エッギーペッギー","icon":"顔アイコン/エッギーペッギー.jpg"},
     {"string":"プリシーラ","icon":"顔アイコン/プリシーラ.jpg"},
     {"string":"ブルターニ","icon":"顔アイコン/ブルターニ.jpg"}
   ]
 }
 ,{"type":"imageskew",
   "question":"これは誰？",
   "image":"キャラ画像/シュミリ.jpg",
   "answers":[
     {"string":"シュミリ","icon":"顔アイコン/シュミリ.jpg"},
     {"string":"テア","icon":"顔アイコン/テア.jpg"},
     {"string":"リンベル","icon":"顔アイコン/リンベル.jpg"},
     {"string":"セレニティー","icon":"顔アイコン/セレニティー.jpg"}
   ]
 }
 ,{"type":"imagezoom",
   "question":"これは誰？",
   "image":"キャラ画像/スウィーティー.jpg",
   "answers":[
     {"string":"スウィーティー","icon":"顔アイコン/スウィーティー.jpg"},
     {"string":"スラ","icon":"顔アイコン/スラ.jpg"},
     {"string":"チャリス","icon":"顔アイコン/チャリス.jpg"},
     {"string":"ポーラー","icon":"顔アイコン/ポーラー.jpg"}
   ]
 }
 ,{"type":"imagepanel",
   "question":"これは誰？",
   "image":"キャラ画像/スラ.jpg",
   "answers":[
     {"string":"スラ","icon":"顔アイコン/スラ.jpg"},
     {"string":"オードリー","icon":"顔アイコン/オードリー.jpg"},
     {"string":"オイフェ","icon":"顔アイコン/オイフェ.jpg"},
     {"string":"シンシア","icon":"顔アイコン/シンシア.jpg"}
   ]
 }
 ,{"type":"imagefilter",
   "question":"これは誰？",
   "image":"キャラ画像/ゾーイ.jpg",
   "answers":[
     {"string":"ゾーイ","icon":"顔アイコン/ゾーイ.jpg"},
     {"string":"チャン","icon":"顔アイコン/チャン.jpg"},
     {"string":"ヨランダ","icon":"顔アイコン/ヨランダ.jpg"},
     {"string":"レベリカ","icon":"顔アイコン/レベリカ.jpg"}
   ]
 }
 ,{"type":"imageskew",
   "question":"これは誰？",
   "image":"キャラ画像/ソルヴェイグ.jpg",
   "answers":[
     {"string":"ソルヴェイグ","icon":"顔アイコン/ソルヴェイグ.jpg"},
     {"string":"パトリシア","icon":"顔アイコン/パトリシア.jpg"},
     {"string":"スノーウィー","icon":"顔アイコン/スノーウィー.jpg"},
     {"string":"華蘭","icon":"顔アイコン/華蘭.jpg"}
   ]
 }
 ,{"type":"imagezoom",
   "question":"これは誰？",
   "image":"キャラ画像/チャリス.jpg",
   "answers":[
     {"string":"チャリス","icon":"顔アイコン/チャリス.jpg"},
     {"string":"スウィーティー","icon":"顔アイコン/スウィーティー.jpg"},
     {"string":"ブレイド","icon":"顔アイコン/ブレイド.jpg"},
     {"string":"ブリーズ・タロー","icon":"顔アイコン/タロー.jpg"}
   ]
 }
 ,{"type":"imagepanel",
   "question":"これは誰？",
   "image":"キャラ画像/チャン.jpg",
   "answers":[
     {"string":"チャン","icon":"顔アイコン/チャン.jpg"},
     {"string":"マギー","icon":"顔アイコン/マギー.jpg"},
     {"string":"マリー","icon":"顔アイコン/マリー.jpg"},
     {"string":"ホイットニー","icon":"顔アイコン/ホイットニー.jpg"}
   ]
 }
 ,{"type":"imagefilter",
   "question":"これは誰？",
   "image":"キャラ画像/チリノ.jpg",
   "answers":[
     {"string":"チリノ","icon":"顔アイコン/チリノ.jpg"},
     {"string":"オードリー","icon":"顔アイコン/オードリー.jpg"},
     {"string":"バソリー","icon":"顔アイコン/バソリー.jpg"},
     {"string":"ソラル","icon":"顔アイコン/ソラル.jpg"}
   ]
 }
 ,{"type":"imageskew",
   "question":"これは誰？",
   "image":"キャラ画像/テア.jpg",
   "answers":[
     {"string":"テア","icon":"顔アイコン/テア.jpg"},
     {"string":"ノーヴァ","icon":"顔アイコン/ノーヴァ.jpg"},
     {"string":"ニア","icon":"顔アイコン/ニア.jpg"},
     {"string":"イヴェット","icon":"顔アイコン/イヴェット.jpg"}
   ]
 }
 ,{"type":"imagezoom",
   "question":"これは誰？",
   "image":"キャラ画像/ナターシャ.jpg",
   "answers":[
     {"string":"ナターシャ","icon":"顔アイコン/ナターシャ.jpg"},
     {"string":"リー","icon":"顔アイコン/リー.jpg"},
     {"string":"鬼影灯","icon":"顔アイコン/鬼影灯.jpg"},
     {"string":"エイダ","icon":"顔アイコン/エイダ.jpg"}
   ]
 }
 ,{"type":"imagepanel",
   "question":"これは誰？",
   "image":"キャラ画像/ニッジー.jpg",
   "answers":[
     {"string":"ニッジー","icon":"顔アイコン/ニッジー.jpg"},
     {"string":"リンベル","icon":"顔アイコン/リンベル.jpg"},
     {"string":"スウィーティー","icon":"顔アイコン/スウィーティー.jpg"},
     {"string":"α-16","icon":"顔アイコン/α-16.jpg"}
   ]
 }
 ,{"type":"imagefilter",
   "question":"これは誰？",
   "image":"キャラ画像/ネプリム.jpg",
   "answers":[
     {"string":"ネプリム","icon":"顔アイコン/ネプリム.jpg"},
     {"string":"シーメ","icon":"顔アイコン/シーメ.jpg"},
     {"string":"ヴェロニカ","icon":"顔アイコン/ヴェロニカ.jpg"},
     {"string":"キーラ","icon":"顔アイコン/キーラ.jpg"}
   ]
 }
 ,{"type":"imageskew",
   "question":"これは誰？",
   "image":"キャラ画像/バソリー.jpg",
   "answers":[
     {"string":"バソリー","icon":"顔アイコン/バソリー.jpg"},
     {"string":"マルマ","icon":"顔アイコン/マルマ.jpg"},
     {"string":"オードリー","icon":"顔アイコン/オードリー.jpg"},
     {"string":"チリノ","icon":"顔アイコン/チリノ.jpg"}
   ]
 }
 ,{"type":"imagezoom",
   "question":"これは誰？",
   "image":"キャラ画像/パトリシア.jpg",
   "answers":[
     {"string":"パトリシア","icon":"顔アイコン/パトリシア.jpg"},
     {"string":"ブルターニ","icon":"顔アイコン/ブルターニ.jpg"},
     {"string":"ロクサーヌ","icon":"顔アイコン/ロクサーヌ.jpg"},
     {"string":"イブリン","icon":"顔アイコン/イブリン.jpg"}
   ]
 }
 ,{"type":"imagepanel",
   "question":"これは誰？",
   "image":"キャラ画像/フーラ.jpg",
   "answers":[
     {"string":"フーラ","icon":"顔アイコン/フーラ.jpg"},
     {"string":"オードリー","icon":"顔アイコン/オードリー.jpg"},
     {"string":"PN26イーレヒース","icon":"顔アイコン/PN26イーレヒース.jpg"},
     {"string":"オイフェ","icon":"顔アイコン/オイフェ.jpg"}
   ]
 }
 ,{"type":"imagefilter",
   "question":"これは誰？",
   "image":"キャラ画像/フェニックス.jpg",
   "answers":[
     {"string":"フェニックス","icon":"顔アイコン/フェニックス.jpg"},
     {"string":"小林団子","icon":"顔アイコン/小林団子.jpg"},
     {"string":"チリノ","icon":"顔アイコン/チリノ.jpg"},
     {"string":"ブレイド","icon":"顔アイコン/ブレイド.jpg"}
   ]
 }
 ,{"type":"imageskew",
   "question":"これは誰？",
   "image":"キャラ画像/ブリーズ・タロー.jpg",
   "answers":[
     {"string":"ブリーズ・タロー","icon":"顔アイコン/タロー.jpg"},
     {"string":"オイフェ","icon":"顔アイコン/オイフェ.jpg"},
     {"string":"フェニックス","icon":"顔アイコン/フェニックス.jpg"},
     {"string":"ホイットニー","icon":"顔アイコン/ホイットニー.jpg"}
   ]
 }
 ,{"type":"imagezoom",
   "question":"これは誰？",
   "image":"キャラ画像/プリシーラ.jpg",
   "answers":[
     {"string":"プリシーラ","icon":"顔アイコン/プリシーラ.jpg"},
     {"string":"ポーラー","icon":"顔アイコン/ポーラー.jpg"},
     {"string":"ミリーナ","icon":"顔アイコン/ミリーナ.jpg"},
     {"string":"グレイヴ","icon":"顔アイコン/グレイヴ.jpg"}
   ]
 }
 ,{"type":"imagepanel",
   "question":"これは誰？",
   "image":"キャラ画像/ブルターニ.jpg",
   "answers":[
     {"string":"ブルターニ","icon":"顔アイコン/ブルターニ.jpg"},
     {"string":"ベルナデット","icon":"顔アイコン/ベルナデット.jpg"},
     {"string":"ニッジー","icon":"顔アイコン/ニッジー.jpg"},
     {"string":"リンベル","icon":"顔アイコン/リンベル.jpg"}
   ]
 }
 ,{"type":"imagefilter",
   "question":"これは誰？",
   "image":"キャラ画像/ブレイド.jpg",
   "answers":[
     {"string":"ブレイド","icon":"顔アイコン/ブレイド.jpg"},
     {"string":"レンゲル","icon":"顔アイコン/レンゲル.jpg"},
     {"string":"チャリス","icon":"顔アイコン/チャリス.jpg"},
     {"string":"ギャレン","icon":"顔アイコン/ギャレン.jpg"}
   ]
 }
 ,{"type":"imageskew",
   "question":"これは誰？",
   "image":"キャラ画像/ヘレーナ.jpg",
   "answers":[
     {"string":"ヘレーナ","icon":"顔アイコン/ヘレーナ.jpg"},
     {"string":"鬼影灯","icon":"顔アイコン/鬼影灯.jpg"},
     {"string":"ネプリム","icon":"顔アイコン/ネプリム.jpg"},
     {"string":"ロサ","icon":"顔アイコン/ロサ.jpg"}
   ]
 }
 ,{"type":"imagezoom",
   "question":"これは誰？",
   "image":"キャラ画像/ホイットニー.jpg",
   "answers":[
     {"string":"ホイットニー","icon":"顔アイコン/ホイットニー.jpg"},
     {"string":"レベリカ","icon":"顔アイコン/レベリカ.jpg"},
     {"string":"鬼影灯","icon":"顔アイコン/鬼影灯.jpg"},
     {"string":"ヘプニェク","icon":"顔アイコン/ヘプニェク.jpg"}
   ]
 }
 ,{"type":"imagepanel",
   "question":"これは誰？",
   "image":"キャラ画像/ポーラ.jpg",
   "answers":[
     {"string":"ポーラ","icon":"顔アイコン/ポーラ.jpg"},
     {"string":"ポーラー","icon":"顔アイコン/ポーラー.jpg"},
     {"string":"ホイットニー","icon":"顔アイコン/ホイットニー.jpg"},
     {"string":"ヘレーナ","icon":"顔アイコン/ヘレーナ.jpg"}
   ]
 }
 ,{"type":"imagefilter",
   "question":"これは誰？",
   "image":"キャラ画像/マーグレット.jpg",
   "answers":[
     {"string":"マーグレット","icon":"顔アイコン/マーグレット.jpg"},
     {"string":"コーレリア","icon":"顔アイコン/コーレリア.jpg"},
     {"string":"グレイヴ","icon":"顔アイコン/グレイヴ.jpg"},
     {"string":"鬼影灯","icon":"顔アイコン/鬼影灯.jpg"}
   ]
 }
 ,{"type":"imageskew",
   "question":"これは誰？",
   "image":"キャラ画像/マギー.jpg",
   "answers":[
     {"string":"マギー","icon":"顔アイコン/マギー.jpg"},
     {"string":"マリー","icon":"顔アイコン/マリー.jpg"},
     {"string":"マルマ","icon":"顔アイコン/マルマ.jpg"},
     {"string":"マーグレット","icon":"顔アイコン/マーグレット.jpg"}
   ]
 }
 ,{"type":"imagezoom",
   "question":"これは誰？",
   "image":"キャラ画像/ミシェリア.jpg",
   "answers":[
     {"string":"ミシェリア","icon":"顔アイコン/ミシェリア.jpg"},
     {"string":"チリノ","icon":"顔アイコン/チリノ.jpg"},
     {"string":"フェヴィア","icon":"顔アイコン/フェヴィア.jpg"},
     {"string":"ヴァイオレット","icon":"顔アイコン/ヴァイオレット.jpg"}
   ]
 }
 ,{"type":"imagepanel",
   "question":"これは誰？",
   "image":"キャラ画像/ミリーナ.jpg",
   "answers":[
     {"string":"ミリーナ","icon":"顔アイコン/ミリーナ.jpg"},
     {"string":"プリシーラ","icon":"顔アイコン/プリシーラ.jpg"},
     {"string":"ローラー","icon":"顔アイコン/ローラー.jpg"},
     {"string":"メガエラ","icon":"顔アイコン/メガエラ.jpg"}
   ]
 }
 ,{"type":"imagefilter",
   "question":"これは誰？",
   "image":"キャラ画像/ミロア.jpg",
   "answers":[
     {"string":"ミロア","icon":"顔アイコン/ミロア.jpg"},
     {"string":"ヴェロニカ","icon":"顔アイコン/ヴェロニカ.jpg"},
     {"string":"鬼影灯","icon":"顔アイコン/鬼影灯.jpg"},
     {"string":"ミシェリア","icon":"顔アイコン/ミシェリア.jpg"}
   ]
 }
 ,{"type":"imageskew",
   "question":"これは誰？",
   "image":"キャラ画像/メイメイ.jpg",
   "answers":[
     {"string":"メイメイ","icon":"顔アイコン/メイメイ.jpg"},
     {"string":"リンベル","icon":"顔アイコン/リンベル.jpg"},
     {"string":"シェール","icon":"顔アイコン/シェール.jpg"},
     {"string":"ミシェリア","icon":"顔アイコン/ミシェリア.jpg"}
   ]
 }
 ,{"type":"imagezoom",
   "question":"これは誰？",
   "image":"キャラ画像/ヨランダ.jpg",
   "answers":[
     {"string":"ヨランダ","icon":"顔アイコン/ヨランダ.jpg"},
     {"string":"フーラ","icon":"顔アイコン/フーラ.jpg"},
     {"string":"マギー","icon":"顔アイコン/マギー.jpg"},
     {"string":"ヴィヴィネ","icon":"顔アイコン/ヴィヴィネ.jpg"}
   ]
 }
 ,{"type":"imagepanel",
   "question":"これは誰？",
   "image":"キャラ画像/リー.jpg",
   "answers":[
     {"string":"リー","icon":"顔アイコン/リー.jpg"},
     {"string":"ナターシャ","icon":"顔アイコン/ナターシャ.jpg"},
     {"string":"レベリカ","icon":"顔アイコン/レベリカ.jpg"},
     {"string":"ヘレーナ","icon":"顔アイコン/ヘレーナ.jpg"}
   ]
 }
 ,{"type":"imagefilter",
   "question":"これは誰？",
   "image":"キャラ画像/リンベル.jpg",
   "answers":[
     {"string":"リンベル","icon":"顔アイコン/リンベル.jpg"},
     {"string":"シーメ","icon":"顔アイコン/シーメ.jpg"},
     {"string":"キーラ","icon":"顔アイコン/キーラ.jpg"},
     {"string":"ポーラ","icon":"顔アイコン/ポーラ.jpg"}
   ]
 }
 ,{"type":"imageskew",
   "question":"これは誰？",
   "image":"キャラ画像/レベリカ.jpg",
   "answers":[
     {"string":"レベリカ","icon":"顔アイコン/レベリカ.jpg"},
     {"string":"ヨランダ","icon":"顔アイコン/ヨランダ.jpg"},
     {"string":"マリー","icon":"顔アイコン/マリー.jpg"},
     {"string":"ポーラー","icon":"顔アイコン/ポーラー.jpg"}
   ]
 }
 ,{"type":"imagezoom",
   "question":"これは誰？",
   "image":"キャラ画像/ローラー.jpg",
   "answers":[
     {"string":"ローラー","icon":"顔アイコン/ローラー.jpg"},
     {"string":"アリエル","icon":"顔アイコン/アリエル.jpg"},
     {"string":"スウィーティー","icon":"顔アイコン/スウィーティー.jpg"},
     {"string":"α-16","icon":"顔アイコン/α-16.jpg"}
   ]
 }
 ,{"type":"imagepanel",
   "question":"これは誰？",
   "image":"キャラ画像/ロクサーヌ.jpg",
   "answers":[
     {"string":"ロクサーヌ","icon":"顔アイコン/ロクサーヌ.jpg"},
     {"string":"ブルターニ","icon":"顔アイコン/ブルターニ.jpg"},
     {"string":"セレニティー","icon":"顔アイコン/セレニティー.jpg"},
     {"string":"マーグレット","icon":"顔アイコン/マーグレット.jpg"}
   ]
 }
 ,{"type":"imagezoom",
   "question":"これは誰？",
   "image":"キャラ画像/鬼影灯.jpg",
   "answers":[
     {"string":"鬼影灯","icon":"顔アイコン/鬼影灯.jpg"},
     {"string":"ヘレーナ","icon":"顔アイコン/ヘレーナ.jpg"},
     {"string":"クリスティーナ","icon":"顔アイコン/クリスティーナ.jpg"},
     {"string":"アンバー","icon":"顔アイコン/アンバー.jpg"}
   ]
 }
]