{
  "レアリティ": "SR",
  "名前": "テア",
  "英名": "Thea",
  "中国名": "希娅",
  "伝記": {
    "簡略": "虹彩異色のせいでいじめられている少女。\n家族がいない彼女は、生き残るため仕方なく窃盗を犯したが、段々その感覚が好きになった。\nあるものを盗む途中に捕まり、手錠をかけられている。\n特製の手錠を開けるため旅に出た。",
    "詳細": "ケゲアのスラム街に暮らす孤児の少女。かなり昔からあらゆる生存スキルを身につけ、盗みの腕を磨いてきた。彼女は盗んだものをお金と交換し、それで自身の生活を維持している。\n時間の流れとともに、自身のスキルが十分熟達した物と考えると、スラム街を離れ、騙しやすい富裕層のいいカモを見つけることにした。これが帝国スラム街の外で窃盗を働く最初で最後の機会であった。テアの窃盗行為はすぐにバレて、捕まった。その時の貴族は彼女のことを面白がり殺さなかった。ただ特製の手錠を掛けてそのまま逃した。開錠の方法を知らないため、永遠にその姿で生きる事になるからである。\nテアは自身の行いを後悔したが、今優先すべきことはこの手錠の開錠する手段を探す事である。様々な場所へ、束縛の解き方を探しに旅へ出た。\n"
  },
  "人柄": {
    "好き": "面白い人間、キラキラしたもの",
    "嫌い": "警察",
    "趣味": "人間観察、万引き",
    "好物": [
      "宝石",
      "共通"
    ]
  },
  "情報": {
    "クラス": "格闘",
    "初期星": "3",
    "誕生日": "7.13",
    "血液型": "A",
    "身長": "150cm",
    "声優": "藍原ことみ"
  },
  "所属": {
    "勢力": "無所属",
    "役職": "詐欺師"
  },
  "誓約": {
    "参列者": [],
    "効果": [
      {
        "効果": "ダメージ",
        "値": "10.0"
      }
    ]
  },
  "精通": {
    "武器": {
      "名前": "突撃武器精通",
      "説明": "突撃武器を使うと、機体の会心率が10%上昇する。"
    },
    "防具": {
      "名前": "軽型パーツ精通",
      "説明": "軽型パーツのみで構成すると、機体の回避率が10%上昇する。"
    }
  },
  "ベースカー": {
    "スキル": {
      "固有": {
        "名前": "情報処理",
        "説明": "情報室内での情報処理に必要な時間を2%短縮する"
      },
      "知恵": {
        "1": {
          "名前": "ケゲア狂騒者D",
          "説明": "ケゲアエリアへの遠征時間を1%短縮する"
        },
        "2": {
          "名前": "ケゲア狂騒者C",
          "説明": "ケゲアエリアへの遠征時間を2%短縮する"
        },
        "3": {
          "名前": "ケゲア狂騒者B",
          "説明": "ケゲアエリアへの遠征時間を3%短縮する"
        },
        "4": {
          "名前": "ケゲア狂騒者A",
          "説明": "ケゲアエリアへの遠征時間を4%短縮する"
        },
        "5": {
          "名前": "ケゲア狂騒者S",
          "説明": "ケゲアエリアへの遠征時間を5%短縮する"
        }
      },
      "製造": {
        "1": {
          "名前": "荒野の堀削機D",
          "説明": "研究室内での施設注文のサイエンスコア獲得量が2%上昇する"
        },
        "2": {
          "名前": "荒野の堀削機C",
          "説明": "研究室内での施設注文のサイエンスコア獲得量が4%上昇する"
        },
        "3": {
          "名前": "荒野の堀削機B",
          "説明": "研究室内での施設注文のサイエンスコア獲得量が6%上昇する"
        },
        "4": {
          "名前": "荒野の堀削機A",
          "説明": "研究室内での施設注文のサイエンスコア獲得量が8%上昇する"
        },
        "5": {
          "名前": "荒野の堀削機S",
          "説明": "研究室内での施設注文のサイエンスコア獲得量が10%上昇する"
        }
      },
      "敏速": {
        "1": {
          "名前": "兵器マニアD",
          "説明": "研究室内での戦備注文時間が2%短縮する"
        },
        "2": {
          "名前": "兵器マニアC",
          "説明": "研究室内での戦備注文時間が4%短縮する"
        },
        "3": {
          "名前": "兵器マニアB",
          "説明": "研究室内での戦備注文時間が6%短縮する"
        },
        "4": {
          "名前": "兵器マニアA",
          "説明": "研究室内での戦備注文時間が8%短縮する"
        },
        "5": {
          "名前": "兵器マニアS",
          "説明": "研究室内での戦備注文時間が10%短縮する"
        }
      },
      "体質": {
        "1": {
          "名前": "ハイクシアー賞金ハンターD",
          "説明": "ハイクシアーエリアの大成功率が2%上昇する"
        },
        "2": {
          "名前": "ハイクシアー賞金ハンターC",
          "説明": "ハイクシアーエリアの大成功率が4%上昇する"
        },
        "3": {
          "名前": "ハイクシアー賞金ハンターB",
          "説明": "ハイクシアーエリアの大成功率が6%上昇する"
        },
        "4": {
          "名前": "ハイクシアー賞金ハンターA",
          "説明": "ハイクシアーエリアの大成功率が8%上昇する"
        },
        "5": {
          "名前": "ハイクシアー賞金ハンターS",
          "説明": "ハイクシアーエリアの大成功率が10%上昇する"
        }
      },
      "感情": {
        "1": {
          "名前": "ファーストフードD",
          "説明": "回収室で食物繊維缶を回収する所要時間を2%短縮する"
        },
        "2": {
          "名前": "ファーストフードC",
          "説明": "回収室で食物繊維缶を回収する所要時間を4%短縮する"
        },
        "3": {
          "名前": "ファーストフードB",
          "説明": "回収室で食物繊維缶を回収する所要時間を6%短縮する"
        },
        "4": {
          "名前": "ファーストフードA",
          "説明": "回収室で食物繊維缶を回収する所要時間を8%短縮する"
        },
        "5": {
          "名前": "ファーストフードS",
          "説明": "回収室で食物繊維缶を回収する所要時間を10%短縮する"
        }
      }
    }
  },
  "ステータス": {
    "LV60": {
      "強固": "505",
      "操作": "493",
      "忍耐": "559",
      "反応": "548",
      "技術": "569"
    },
    "星6": {
      "強固": "303",
      "操作": "295",
      "忍耐": "335",
      "反応": "328",
      "技術": "341"
    },
    "覚醒": {
      "SSR": {
        "強固": "235",
        "操作": "225",
        "忍耐": "260",
        "反応": "250",
        "技術": "260"
      }
    },
    "フル潜在": {
      "耐久": "938",
      "攻撃": "84",
      "防御": "64",
      "回避": "84",
      "会心": "24",
      "対エリートダメージ軽減": "10.0",
      "強固": "855",
      "操作": "668",
      "忍耐": "710",
      "対ボスダメージ軽減": "5.0",
      "反応": "846",
      "技術": "554",
      "命中": "554",
      "対エリートダメージ上昇": "8.0",
      "対ボスダメージ上昇": "8.0",
      "ダメージ": "7.0",
      "ダメージ軽減": "14.0",
      "潜在スキル": "3",
      "攻撃速度": "6.0",
      "移動速度": "6.0"
    },
    "変換倍率": {
      "強固": "20.8146",
      "忍耐": "1.6505",
      "反応": "2.3711",
      "技術": "3.5135",
      "操作": "2.381"
    },
    "能力合計": {
      "強固": "1898",
      "操作": "1681",
      "忍耐": "1864",
      "反応": "1972",
      "技術": "1724"
    },
    "ステ合計": {
      "耐久": "40444",
      "攻撃": "4086",
      "防御": "3141",
      "回避": "4760",
      "会心": "6081"
    }
  },
  "スキル": {
    "AS": {
      "名前": "本当に申し訳ございません",
      "1": {
        "説明": "敵単体に808%のダメージを与え、敵を撃破した場合は味方全体に会心率が10%上昇する効果を10秒間付与する。"
      },
      "2": {
        "説明": "敵単体に930%のダメージを与え、敵を撃破した場合は味方全体に会心率が10%上昇する効果を10秒間付与する。"
      },
      "3": {
        "説明": "敵単体に1053%のダメージを与え、敵を撃破した場合は味方全体に会心率が10%上昇する効果を10秒間付与する。"
      },
      "4": {
        "説明": "敵単体に1175%のダメージを与え、敵を撃破した場合は味方全体に会心率が10%上昇する効果を10秒間付与する。"
      },
      "5": {
        "説明": "敵単体に1420%のダメージを与え、敵を撃破した場合は味方全体に会心率が10%上昇する効果を10秒間付与する。"
      }
    },
    "P1": {
      "名前": "会心強化",
      "1": {
        "説明": "戦闘中、自身の会心率を8%上昇する"
      },
      "2": {
        "説明": "戦闘中、自身の会心率を9.5%上昇する"
      },
      "3": {
        "説明": "戦闘中、自身の会心率を11%上昇する"
      },
      "4": {
        "説明": "戦闘中、自身の会心率を12.5%上昇する"
      },
      "5": {
        "説明": "戦闘中、自身の会心率を15.5%上昇する"
      }
    },
    "P2": {
      "名前": "キリングフィーバー",
      "1": {
        "説明": "戦闘中、テアの攻撃速度が10%上昇する"
      },
      "2": {
        "説明": "戦闘中、テアの攻撃速度が12%上昇する"
      },
      "3": {
        "説明": "戦闘中、テアの攻撃速度が14%上昇する"
      },
      "4": {
        "説明": "戦闘中、テアの攻撃速度が16%上昇する"
      },
      "5": {
        "説明": "戦闘中、テアの攻撃速度が20%上昇する"
      }
    },
    "P3": {
      "名前": "会心ダメージ強化",
      "1": {
        "説明": "戦闘中、自身の会心ダメージが19.5%上昇する"
      },
      "2": {
        "説明": "戦闘中、自身の会心ダメージが23.5%上昇する"
      },
      "3": {
        "説明": "戦闘中、自身の会心ダメージが27%上昇する"
      },
      "4": {
        "説明": "戦闘中、自身の会心ダメージが31%上昇する"
      },
      "5": {
        "説明": "戦闘中、自身の会心ダメージが39%上昇する"
      }
    },
    "PS": {
      "1": {
        "名前": "フィーバーアタックⅠ",
        "説明": "戦闘中、自身の与ダメージが2%上昇する。"
      },
      "2": {
        "名前": "フィーバーアタックⅡ",
        "説明": "戦闘中、自身の与ダメージが2%上昇し、BOSSからの被ダメージが3%減少する。"
      },
      "3": {
        "名前": "フィーバーアタックⅢ",
        "説明": "戦闘中、自身の与ダメージが7%上昇し、BOSSからの被ダメージが3%減少する。"
      },
      "名前": "フィーバーアタックⅢ"
    }
  },
  "スキン": {
    "1": {
      "名前": "テア",
      "ボイス": {
        "参加": "前々からお名前を耳にしておりました、団長様。手かせ、外してもらえる？",
        "対話1": "こんなにも目立っていたら、こそ泥なんかできるわけないでしょ？",
        "対話2": "じっと見つめないでくれよ。",
        "対話3": "この手かせ？僕のシンボルだよ。はは、嘘だよ。",
        "対話4": "今のスタイルが結構気に入ってるよ。なんちゃって。",
        "対話5": "力任せの解体はダメだよ。死んじゃうから。",
        "対話6": "ほかの人はオッドアイとか…そんな迷信的なものが気になってるようだけど、団長なら…そんなことしないよね？",
        "対話7": "ん？取ったものを返せって？そっか……あれは取っちゃいけないものだったのか？",
        "対話8": "うまく活用すれば、このチェーンで簡単に人を殺せるんだよ、ふふ。",
        "対話9": "朝目を覚ますたびに、一生懸命笑ってみるようにしているんだ。",
        "誓約": "そう言ってもらえると嬉しいけど、誰かと一生付き合っていくつもりはないんだよ、団長。",
        "待機": "ふぅ……ちょっと退屈。",
        "誕生日": "誕生日おめでと、団長。これ、プレゼント。言っとくけど、これは盗んだものじゃないからね？",
        "部隊編入": "ロボットの運転くらい大丈夫だよ。",
        "戦闘開始": "行ってくるよ。",
        "出撃": "攻撃するなら、うちのメンバーたちを優先して。",
        "操作変更": "グズグズしすぎ。",
        "戦闘不能": "ありゃりゃ。",
        "スキル準備": "スキル準備完了。",
        "スキル1": "無駄だよ、無駄。",
        "スキル2": "みなさんに最高の敬意を。",
        "HP低下": "早く逃げたほうがよかった。",
        "勝利": "弱すぎるんじゃない？",
        "敗北": "そんなに頑張らなくてもいいんじゃない？",
        "マップ配置": "チーム準備完了。",
        "強化": "サンキュー。",
        "改造": "悪くない。",
        "スキル上昇": "テクニックは重要だから。",
        "アイテム発見": "アイテム、発見したよ。",
        "敵発見": "敵が来たよ。",
        "移動": "チーム、移動中。",
        "拠点占拠": "拠点のコントロール権限を取得したよ。",
        "補給獲得": "補給物資、発見したよ。",
        "呼び1": "団長",
        "呼び2": "ボス",
        "呼び3": "指揮官",
        "呼び4": "お兄ちゃん",
        "呼び5": "おじさん！",
        "呼び6": "旦那様"
      }
    }
  }
}
