{
  "レアリティ": "SSR",
  "名前": "ミナヅキ",
  "英名": "Minazuki",
  "中国名": "六月",
  "伝記": {
    "簡略": "「ハイクシアー国立学院」パイロット実験クラスの転校生。\n変な性格で、自身を宇宙人だと心から宣言したが、誰も嘘かどうか判断できない。\n根は優しくて、共感力のあるいい子だ。人間とふわふわとしたものが大好き。遠距離で電気またはメカを操作できる。頭にある「触角」がハイテク機能なのかどうかは知られていない。",
    "詳細": "二学期が始まり、ハイクシアー国立学院パイロット実験クラスは転校生ミナヅキを迎え入れた。彼女の自己紹介は少し特殊で、真剣に自身が宇宙人だと語った。彼女は遠き「128.133.4685星」出身で、もうすぐ大学を卒業するところだったと言うのだ。しかも今は、空間管理局の公務員になるため、この星を生体観測するインターンシップをしている最中らしい。能力はサイコで、電気を操ったり、他人を洗脳したりできる。ミナヅキと名乗ったのはこの星に来た時がちょうど六月だったから。因みに自身の誕生日も地球に来た日にしている。定期的に祖国へ観測資料を送るために、話しているとき「ピーピー」と機械的な音が鳴る。\n頭にはアンテナのようなものがあり、宇宙人特有の触角だとミナヅキは言った。悪戯で彼女の触角を引っ張り、嘘をばらそうとした者がいたが、結局血が止まらずに噴出していた。ミナヅキは顔色一つ変えずに触角を取り戻し、元の位置に挿してようやく血が止まった。\nミナヅキはどうやらサイコでマシンやメカを操れるようだが、それは宇宙人の触角によって引き起こされたハイテク機能かどうかは知らない。この世界で宇宙人がいると証明できるものがないからだ。\nミナヅキは父親と暮らしている。宇宙人なのにどうして地球に父親がいるのかと質問された時は決まって、生活環境を整えるために赤の他人を洗脳して、父親だと思い込ませたと答える。彼女は人間好きで、友達を作ることも好きだ。反応がちょっと遅いことを除けば、彼女は共感力のあるやさしい子だ。しかし彼女の話については真偽を判断できる人がいないし、彼女はいつも真面目な顔で変わった事を言うので、クラスメートはちょっと困っている。彼女はアニメと漫画が大好きのため、そのせいで変になったかもしれない。彼女と気楽に話し合える話題はおそらくグルメについてだけだろう……\n"
  },
  "人柄": {
    "好き": "人間、フワフワしたもの",
    "嫌い": "虫",
    "趣味": "グルメ、漫画、アニメ",
    "好物": [
      "食べ物",
      "共通"
    ]
  },
  "情報": {
    "クラス": "投射",
    "初期星": "3",
    "誕生日": "6.2",
    "血液型": "B",
    "身長": "162cm",
    "声優": "城崎琳子"
  },
  "所属": {
    "勢力": "ハイクシアー",
    "役職": "学生"
  },
  "誓約": {
    "参列者": [],
    "効果": [
      {
        "効果": "耐久",
        "値": "15.000001"
      }
    ]
  },
  "精通": {
    "武器": {
      "名前": "投射武器精通",
      "説明": "投射武器を使うと、機体の与ダメージが10%上昇する。"
    },
    "防具": {
      "名前": "重型パーツ精通",
      "説明": "重型パーツのみで構成すると、機体の耐久が10%上昇する。"
    }
  },
  "ベースカー": {
    "スキル": {
      "固有": {
        "名前": "触角",
        "説明": "電力室での電力の生産周期が2%短縮する"
      },
      "知恵": {
        "1": {
          "名前": "感電D",
          "説明": "回収室で電力を回収すると獲得量が2%上昇する"
        },
        "2": {
          "名前": "感電C",
          "説明": "回収室で電力を回収すると獲得量が4%上昇する"
        },
        "3": {
          "名前": "感電B",
          "説明": "回収室で電力を回収すると獲得量が6%上昇する"
        },
        "4": {
          "名前": "感電A",
          "説明": "回収室で電力を回収すると獲得量が8%上昇する"
        },
        "5": {
          "名前": "感電S",
          "説明": "回収室で電力を回収すると獲得量が10%上昇する"
        }
      },
      "製造": {
        "1": {
          "名前": "ケゲアエネルギー商人D",
          "説明": "ケゲアエリアへの遠征で獲得する電力が2%上昇する"
        },
        "2": {
          "名前": "ケゲアエネルギー商人C",
          "説明": "ケゲアエリアへの遠征で獲得する電力が4%上昇する"
        },
        "3": {
          "名前": "ケゲアエネルギー商人B",
          "説明": "ケゲアエリアへの遠征で獲得する電力が6%上昇する"
        },
        "4": {
          "名前": "ケゲアエネルギー商人A",
          "説明": "ケゲアエリアへの遠征で獲得する電力が8%上昇する"
        },
        "5": {
          "名前": "ケゲアエネルギー商人S",
          "説明": "ケゲアエリアへの遠征で獲得する電力が10%上昇する"
        }
      },
      "敏速": {
        "1": {
          "名前": "戦争研究員D",
          "説明": "研究室内での戦備注文のサイエンスコア獲得量が2%上昇する"
        },
        "2": {
          "名前": "戦争研究員C",
          "説明": "研究室内での戦備注文のサイエンスコア獲得量が4%上昇する"
        },
        "3": {
          "名前": "戦争研究員B",
          "説明": "研究室内での戦備注文のサイエンスコア獲得量が6%上昇する"
        },
        "4": {
          "名前": "戦争研究員A",
          "説明": "研究室内での戦備注文のサイエンスコア獲得量が8%上昇する"
        },
        "5": {
          "名前": "戦争研究員S",
          "説明": "研究室内での戦備注文のサイエンスコア獲得量が10%上昇する"
        }
      },
      "体質": {
        "1": {
          "名前": "ハイクシアー食いしん坊D",
          "説明": "ハイクシアーエリアへの遠征で獲得する食物が2%上昇する"
        },
        "2": {
          "名前": "ハイクシアー食いしん坊C",
          "説明": "ハイクシアーエリアへの遠征で獲得する食物が4%上昇する"
        },
        "3": {
          "名前": "ハイクシアー食いしん坊B",
          "説明": "ハイクシアーエリアへの遠征で獲得する食物が6%上昇する"
        },
        "4": {
          "名前": "ハイクシアー食いしん坊A",
          "説明": "ハイクシアーエリアへの遠征で獲得する食物が8%上昇する"
        },
        "5": {
          "名前": "ハイクシアー食いしん坊S",
          "説明": "ハイクシアーエリアへの遠征で獲得する食物が10%上昇する"
        }
      },
      "感情": {
        "1": {
          "名前": "親水体質D",
          "説明": "水源室での水の生産周期が2%短縮する"
        },
        "2": {
          "名前": "親水体質C",
          "説明": "水源室での水の生産周期が4%短縮する"
        },
        "3": {
          "名前": "親水体質B",
          "説明": "水源室での水の生産周期が6%短縮する"
        },
        "4": {
          "名前": "親水体質A",
          "説明": "水源室での水の生産周期が8%短縮する"
        },
        "5": {
          "名前": "親水体質S",
          "説明": "水源室での水の生産周期が10%短縮する"
        }
      }
    }
  },
  "ステータス": {
    "LV60": {
      "強固": "609",
      "操作": "616",
      "忍耐": "653",
      "反応": "714",
      "技術": "689"
    },
    "星6": {
      "強固": "365",
      "操作": "370",
      "忍耐": "391",
      "反応": "428",
      "技術": "413"
    },
    "フル潜在": {
      "耐久": "1114",
      "攻撃": "126",
      "防御": "92",
      "回避": "102",
      "会心": "32",
      "対エリートダメージ軽減": "0.1",
      "強固": "981",
      "操作": "975",
      "忍耐": "975",
      "対ボスダメージ軽減": "0.1",
      "反応": "1033",
      "技術": "717",
      "命中": "717",
      "対エリートダメージ上昇": "0.1",
      "対ボスダメージ上昇": "0.1",
      "ダメージ": "0.1",
      "ダメージ軽減": "0.1",
      "潜在スキル": "3.0",
      "攻撃速度": "0.1",
      "移動速度": "0.1"
    },
    "変換倍率": {
      "強固": "22.1021",
      "操縦": "2.5",
      "忍耐": "1.6505",
      "反応": "1.6505",
      "技術": "2.5"
    }
  },
  "スキル": {
    "AS": {
      "名前": "ファーストコンタクト",
      "1": {
        "説明": "石碑を召喚して一定範囲内の敵全体に221%のダメージを与える。最も耐久の低い味方に3秒間「魅影」効果を付与する。\n魅影効果：付与対象が受けるダメージを耐久上限*10%分吸収可能。\n専用機解放後のスキル効果：\n幽嬰を召喚して一定範囲の敵全体に265%のダメージを与える。最も耐久の低い味方に3秒間「魅影」効果を付与する。\n魅影効果：付与対象が受けるダメージを耐久上限*15%分吸収可能。持続時間終了またはダメージ吸収が上限に達した場合、魅影は爆発し、範囲内にいる敵に合計の吸収ダメージを均等に分け与え、怨霊効果を付与する。\n怨霊効果：耐久の回復効果が100%減少、効果は10秒持続する。"
      },
      "2": {
        "説明": "石碑を召喚して一定範囲内の敵全体に259%のダメージを与える。最も耐久の低い味方に3.5秒間「魅影」効果を付与する。\n魅影効果：付与対象が受けるダメージを耐久上限*10%分吸収可能。\n専用機解放後のスキル効果：\n幽嬰を召喚して一定範囲の敵全体に310%のダメージを与える。最も耐久の低い味方に3.5秒間「魅影」効果を付与する。\n魅影効果：付与対象が受けるダメージを耐久上限*15%分吸収可能。持続時間終了またはダメージ吸収が上限に達した場合、魅影は爆発し、範囲内にいる敵に合計の吸収ダメージを均等に分け与え、怨霊効果を付与する。\n怨霊効果：耐久の回復効果が100%減少、効果は10秒持続する。"
      },
      "3": {
        "説明": "石碑を召喚して一定範囲内の敵全体に296%のダメージを与える。最も耐久の低い味方に4秒間「魅影」効果を付与する。\n魅影効果：付与対象が受けるダメージを耐久上限*10%分吸収可能。\n専用機解放後のスキル効果：\n幽嬰を召喚して一定範囲の敵全体に355%のダメージを与える。最も耐久の低い味方に4秒間「魅影」効果を付与する。\n魅影効果：付与対象が受けるダメージを耐久上限*15%分吸収可能。持続時間終了またはダメージ吸収が上限に達した場合、魅影は爆発し、範囲内にいる敵に合計の吸収ダメージを均等に分け与え、怨霊効果を付与する。\n怨霊効果：耐久の回復効果が100%減少、効果は10秒持続する。"
      },
      "4": {
        "説明": "石碑を召喚して一定範囲内の敵全体に334%のダメージを与える。最も耐久の低い味方に4.5秒間「魅影」効果を付与する。\n魅影効果：付与対象が受けるダメージを耐久上限*10%分吸収可能。\n専用機解放後のスキル効果：\n幽嬰を召喚して一定範囲の敵全体に400%のダメージを与える。最も耐久の低い味方に4.5秒間「魅影」効果を付与する。\n魅影効果：付与対象が受けるダメージを耐久上限*15%分吸収可能。持続時間終了またはダメージ吸収が上限に達した場合、魅影は爆発し、範囲内にいる敵に合計の吸収ダメージを均等に分け与え、怨霊効果を付与する。\n怨霊効果：耐久の回復効果が100%減少、効果は10秒持続する。"
      },
      "5": {
        "説明": "石碑を召喚して一定範囲内の敵全体に409%のダメージを与える。最も耐久の低い味方に5秒間「魅影」効果を付与する。\n魅影効果：付与対象が受けるダメージを耐久上限*10%分吸収可能。\n専用機解放後のスキル効果：\n幽嬰を召喚して一定範囲の敵全体に490%のダメージを与える。最も耐久の低い味方に5秒間「魅影」効果を付与する。\n魅影効果：付与対象が受けるダメージを耐久上限*15%分吸収可能。持続時間終了またはダメージ吸収が上限に達した場合、魅影は爆発し、範囲内にいる敵に合計の吸収ダメージを均等に分け与え、怨霊効果を付与する。\n怨霊効果：耐久の回復効果が100%減少、効果は10秒持続する。"
      }
    },
    "P1": {
      "名前": "エイリアンバリア",
      "1": {
        "説明": "ミナヅキが攻撃時、9%の確率で最もHPが低い味方に耐久*10%分のダメージを吸収可能なバリアを付与し、バリアは5秒間持続する。バリアは1秒ごとにダメージ吸収量が20%減少する。この効果は12秒ごとに最大1回発動可能。\n専用機解放後のスキル効果：\nミナヅキが攻撃時、9%の確率で最もHPが低い味方に耐久*15%分のダメージを吸収可能なバリアを付与し、バリアは5秒間持続する。バリアは1秒ごとにダメージ吸収量が20%減少する。この効果は12秒ごとに最大1回発動可能。\nバリアが消失時、付与対象の与ダメージが15%上昇する効果を5秒間獲得する。"
      },
      "2": {
        "説明": "ミナヅキが攻撃時、12%の確率で最もHPが低い味方に耐久*10%分のダメージを吸収可能なバリアを付与し、バリアは5秒間持続する。バリアは1秒ごとにダメージ吸収量が20%減少する。この効果は12秒ごとに最大1回発動可能。\n専用機解放後のスキル効果：\nミナヅキが攻撃時、12%の確率で最もHPが低い味方に耐久*15%分のダメージを吸収可能なバリアを付与し、バリアは5秒間持続する。バリアは1秒ごとにダメージ吸収量が20%減少する。この効果は12秒ごとに最大1回発動可能。\nバリアが消失時、付与対象の与ダメージが15%上昇する効果を5秒間獲得する。"
      },
      "3": {
        "説明": "ミナヅキが攻撃時、15%の確率で最もHPが低い味方に耐久*10%分のダメージを吸収可能なバリアを付与し、バリアは5秒間持続する。バリアは1秒ごとにダメージ吸収量が20%減少する。この効果は12秒ごとに最大1回発動可能。\n専用機解放後のスキル効果：\nミナヅキが攻撃時、15%の確率で最もHPが低い味方に耐久*15%分のダメージを吸収可能なバリアを付与し、バリアは5秒間持続する。バリアは1秒ごとにダメージ吸収量が20%減少する。この効果は12秒ごとに最大1回発動可能。\nバリアが消失時、付与対象の与ダメージが30%上昇する効果を5秒間獲得する。"
      },
      "4": {
        "説明": "ミナヅキが攻撃時、18%の確率で最もHPが低い味方に耐久*10%分のダメージを吸収可能なバリアを付与し、バリアは5秒間持続する。バリアは1秒ごとにダメージ吸収量が20%減少する。この効果は12秒ごとに最大1回発動可能。\n専用機解放後のスキル効果：\nミナヅキが攻撃時、18%の確率で最もHPが低い味方に耐久*15%分のダメージを吸収可能なバリアを付与し、バリアは5秒間持続する。バリアは1秒ごとにダメージ吸収量が20%減少する。この効果は12秒ごとに最大1回発動可能。\nバリアが消失時、付与対象の与ダメージが30%上昇する効果を5秒間獲得する。"
      },
      "5": {
        "説明": "ミナヅキが攻撃時、21%の確率で最もHPが低い味方に耐久*10%分のダメージを吸収可能なバリアを付与し、バリアは5秒間持続する。バリアは1秒ごとにダメージ吸収量が20%減少する。この効果は12秒ごとに最大1回発動可能。\n専用機解放後のスキル効果：\nミナヅキが攻撃時、21%の確率で最もHPが低い味方に耐久*15%分のダメージを吸収可能なバリアを付与し、バリアは5秒間持続する。バリアは1秒ごとにダメージ吸収量が20%減少する。この効果は12秒ごとに最大1回発動可能。\nバリアが消失時、付与対象の与ダメージが45%上昇する効果を5秒間獲得する。"
      }
    },
    "P2": {
      "名前": "電波妨害",
      "1": {
        "説明": "20秒ごとに、自身の耐久1％と引き替えに、自身を除くHPが最も低い味方に5秒間の耐久持続回復(1秒ごとに1.2％回復)の効果を付与する。この効果は持続時間リセット不可、重ね掛け不可。HP不足時に発動するとミナヅキは戦闘不能となる。\n専用機解放後のスキル効果：\n20秒ごとに、自身の耐久0.5％と引き替えに、HPが最も低い味方に5秒間の耐久持続回復(1秒ごとに1.2％回復)の効果を付与する。この効果は持続時間リセット不可、重ね掛け不可。HP不足時に発動するとミナヅキは戦闘不能となる。"
      },
      "2": {
        "説明": "20秒ごとに、自身の耐久1％と引き替えに、自身を除くHPが最も低い味方に5秒間の耐久持続回復(1秒ごとに1.4％回復)の効果を付与する。この効果は持続時間リセット不可、重ね掛け不可。HP不足時に発動するとミナヅキは戦闘不能となる。\n専用機解放後のスキル効果：\n20秒ごとに、自身の耐久0.5％と引き替えに、HPが最も低い味方に5秒間の耐久持続回復(1秒ごとに1.4％回復)の効果を付与する。この効果は持続時間リセット不可、重ね掛け不可。HP不足時に発動するとミナヅキは戦闘不能となる。"
      },
      "3": {
        "説明": "20秒ごとに、自身の耐久1％と引き替えに、自身を除くHPが最も低い味方に5秒間の耐久持続回復(1秒ごとに1.6％回復)の効果を付与する。この効果は持続時間リセット不可、重ね掛け不可。HP不足時に発動するとミナヅキは戦闘不能となる。\n専用機解放後のスキル効果：\n20秒ごとに、自身の耐久0.5％と引き替えに、HPが最も低い味方に5秒間の耐久持続回復(1秒ごとに1.6％回復)の効果を付与する。この効果は持続時間リセット不可、重ね掛け不可。HP不足時に発動するとミナヅキは戦闘不能となる。"
      },
      "4": {
        "説明": "20秒ごとに、自身の耐久1％と引き替えに、自身を除くHPが最も低い味方に5秒間の耐久持続回復(1秒ごとに1.8％回復)の効果を付与する。この効果は持続時間リセット不可、重ね掛け不可。HP不足時に発動するとミナヅキは戦闘不能となる。\n専用機解放後のスキル効果：\n20秒ごとに、自身の耐久0.5％と引き替えに、HPが最も低い味方に5秒間の耐久持続回復(1秒ごとに1.8％回復)の効果を付与する。この効果は持続時間リセット不可、重ね掛け不可。HP不足時に発動するとミナヅキは戦闘不能となる。"
      },
      "5": {
        "説明": "20秒ごとに、自身の耐久1％と引き替えに、自身を除くHPが最も低い味方に5秒間の耐久持続回復(1秒ごとに2％回復)の効果を付与する。この効果は持続時間リセット不可、重ね掛け不可。HP不足時に発動するとミナヅキは戦闘不能となる。\n専用機解放後のスキル効果：\n20秒ごとに、自身の耐久0.5％と引き替えに、HPが最も低い味方に5秒間の耐久持続回復(1秒ごとに2％回復)の効果を付与する。この効果は持続時間リセット不可、重ね掛け不可。HP不足時に発動するとミナヅキは戦闘不能となる。"
      }
    },
    "P3": {
      "名前": "母星儀式",
      "1": {
        "説明": "味方が戦闘不能になった場合、ミナヅキは自身のHPを80%消費(HP不足の場合は戦闘不能となる)する代わりに対象を復帰させる。復帰対象の耐久はミナヅキのHP*30%分となる。戦闘不能な味方が複数存在する場合は最初に戦闘不能となった味方が対象となる。\nこの効果は60秒ごとに最大1回発動可能、復帰効果を持つスキルと同時に発動可能。\n専用機解放後のスキル効果：\n味方が戦闘不能になった場合、ミナヅキは自身のHPを80%消費(HP不足の場合は戦闘不能となる)する代わりに対象を復帰させる。復帰対象のHPはミナヅキのHP*30%分となり、与ダメージ、会心率が6%上昇する効果を戦闘終了まで獲得する。戦闘不能な味方が複数存在する場合は最初に戦闘不能となった味方が対象となる。\nこの効果は60秒ごとに最大1回発動可能、復帰効果を持つスキルと同時に発動可能。"
      },
      "2": {
        "説明": "味方が戦闘不能になった場合、ミナヅキは自身のHPを75%消費(HP不足の場合は戦闘不能となる)する代わりに対象を復帰させる。復帰対象のHPはミナヅキのHP*35%分となる。戦闘不能な味方が複数存在する場合は最初に戦闘不能となった味方が対象となる。\nこの効果は60秒ごとに最大1回発動可能、復帰効果を持つスキルと同時に発動可能。\n専用機解放後のスキル効果：\n味方が戦闘不能になった場合、ミナヅキは自身のHPを75%消費(HP不足の場合は戦闘不能となる)する代わりに対象を復帰させる。復帰対象のHPはミナヅキのHP*35%分となり、与ダメージ、会心率が7%上昇する効果を戦闘終了まで獲得する。戦闘不能な味方が複数存在する場合は最初に戦闘不能となった味方が対象となる。\nこの効果は60秒ごとに最大1回発動可能、復帰効果を持つスキルと同時に発動可能。"
      },
      "3": {
        "説明": "味方が戦闘不能になった場合、ミナヅキは自身のHPを70%消費(HP不足の場合は戦闘不能となる)する代わりに対象を復帰させる。復帰対象のHPはミナヅキのHP*40%分となる。戦闘不能な味方が複数存在する場合は最初に戦闘不能となった味方が対象となる。\nこの効果は60秒ごとに最大1回発動可能、復帰効果を持つスキルと同時に発動可能。\n専用機解放後のスキル効果：\n味方が戦闘不能になった場合、ミナヅキは自身のHPを70%消費(HP不足の場合は戦闘不能となる)する代わりに対象を復帰させる。復帰対象のHPはミナヅキのHP*40%分となり、与ダメージ、会心率が8%上昇する効果を戦闘終了まで獲得する。戦闘不能な味方が複数存在する場合は最初に戦闘不能となった味方が対象となる。\nこの効果は60秒ごとに最大1回発動可能、復帰効果を持つスキルと同時に発動可能。"
      },
      "4": {
        "説明": "味方が戦闘不能になった場合、ミナヅキは自身のHPを65%消費(HP不足の場合は戦闘不能となる)する代わりに対象を復帰させる。復帰対象のHPはミナヅキのHP*45%分となる。戦闘不能な味方が複数存在する場合は最初に戦闘不能となった味方が対象となる。\nこの効果は60秒ごとに最大1回発動可能、復帰効果を持つスキルと同時に発動可能。\n専用機解放後のスキル効果：\n味方が戦闘不能になった場合、ミナヅキは自身のHPを60%消費(HP不足の場合は戦闘不能となる)する代わりに対象を復帰させる。復帰対象のHPはミナヅキのHP*45%分となり、与ダメージ、会心率が9%上昇する効果を戦闘終了まで獲得する。戦闘不能な味方が複数存在する場合は最初に戦闘不能となった味方が対象となる。\nこの効果は60秒ごとに最大1回発動可能、復帰効果を持つスキルと同時に発動可能。"
      },
      "5": {
        "説明": "味方が戦闘不能になった場合、ミナヅキは自身のHPを60%消費(HP不足の場合は戦闘不能となる)する代わりに対象を復帰させる。復帰対象のHPはミナヅキのHP*50%分となる。戦闘不能な味方が複数存在する場合は最初に戦闘不能となった味方が対象となる。\nこの効果は60秒ごとに最大1回発動可能、復帰効果を持つスキルと同時に発動可能。\n専用機解放後のスキル効果：\n味方が戦闘不能になった場合、ミナヅキは自身のHPを50%消費(HP不足の場合は戦闘不能となる)する代わりに対象を復帰させる。復帰対象のHPはミナヅキのHP*50%分となり、与ダメージ、会心率が10%上昇する効果を戦闘終了まで獲得する。戦闘不能な味方が複数存在する場合は最初に戦闘不能となった味方が対象となる。\nこの効果は60秒ごとに最大1回発動可能、復帰効果を持つスキルと同時に発動可能。"
      }
    }
  },
  "スキン": {
    "1": {
      "名前": "ミナヅキ",
      "ボイス": {
        "参加": "128.133.4685星から来た、ミナヅキ。もうすぐ卒業する大学生ピ。",
        "対話1": "これは私たちの種族独自の触角ピピ。",
        "対話2": "6月にこの星に来たから、ミナヅキと名付けたピピ。",
        "対話3": "父は私に洗脳された人間ピ。",
        "対話4": "うう……どうしてこの星に虫なんて…ピピ……",
        "対話5": "大丈夫、元に戻せば血が止まる……ほら、ピピ。",
        "対話6": "私の任務は、この星の生態を監視することピ、人間は大好きピピ。",
        "対話7": "地球は食べ物が美味しいし、漫画も面白い。この星が気に入ったピピ。",
        "対話8": "ここの言葉で言うと、私の能力は「念」って言うピ。ロボットと電気機器を操れるピ。",
        "対話9": "いつか団長に、ミナヅキの故郷を紹介したいピ。",
        "誓約": "私に？わあ、ありがとう！もふもふ大好きピピ！",
        "待機": "全然待たせてないよ。それに、この漫画が面白いピ！",
        "誕生日": "誕生日おめでとうピー。でも、団長には触覚がないし、母星の儀式を感じ取れないピ。",
        "部隊編入": "到着ーーピピー。",
        "戦闘開始": "本気で行くピ。",
        "出撃": "これも観察の一部ピピ。",
        "操作変更": "ミナヅキ、助けにやって来たよピピ。",
        "戦闘不能": "悲しまないで……私の意識は母星に帰って、永遠に生き続けるピ……",
        "スキル準備": "母星の力を感じたピ。",
        "スキル1": "ごめんなさい、どいてピ。",
        "スキル2": "痛い？こんなことしたくないピ。",
        "HP低下": "避難のために母星に帰るピ。",
        "勝利": "わーい！これでパフォーマンス評価の成績が上がるピ！",
        "敗北": "学校の模擬戦とは全然違うピ……",
        "マップ配置": "チームが位置に付いたピ。",
        "強化": "パフォーマンス評価がまた上がったピ。",
        "改造": "触角が伸びたピ。",
        "スキル上昇": "もしかしたら、インターンシップ評価で通過をもらえるピ。",
        "アイテム発見": "よくわからないピ。",
        "敵発見": "触角さえ触らなければ、なにをしてもいいピピ。",
        "移動": "ピーピーピー",
        "拠点占拠": "ここはミナヅキがもらったピ。",
        "補給獲得": "補給ピピ。",
        "呼び1": "団長",
        "呼び2": "社長（ボス）",
        "呼び3": "指揮官",
        "呼び4": "お兄さん",
        "呼び5": "先生",
        "呼び6": "旦那様"
      }
    },
    "2": {
      "名前": "宇宙浮遊\u3000ミナヅキ"
    }
  }
}
