{
  "名前": "導き",
  "説明": "人物の目線や動きで、見る者の注目ポイントを誘導している。",
  "種類": "中型脚部",
  "製造情報": {
    "陣営": "無所属",
    "型名": "ジョット",
    "説明": "絵を描いているだけだ。",
    "設計者": "ローレル",
    "製造者": "？？？"
  },
  "基本性能": {
    "貫通抵抗": 1,
    "衝撃耐性": {
      "基礎": 240,
      "衝撃減衰": 80,
      "ノックバック": 0.35
    },
    "移動速度": {
      "通常": 7,
      "ダッシュ": 15,
      "後退": 7
    }
  },
  "専用機性能": {
    "貫通抵抗": 1.5,
    "衝撃耐性": {
      "基礎": 290,
      "衝撃減衰": 50,
      "ノックバック": 0.45
    },
    "移動速度": {
      "通常": 7,
      "ダッシュ": 15,
      "後退": 7
    }
  }
}
